{"metadata":{"dataVersion":"2","matchId":"EUW1_7744691005","participants":["jcW3TDS_ov7wUlBYKRZGbvecykB7ZIusAuIIddY6NE3rUun13QuyRmK9MnOYP9JeqWnyWq3J8cSKQA","RunCLgHixgLPXO6tjcGx4ku64FI3oXN6ECqBo80X2r7As0h69v5GYjnJqR-5H6ccHV8QU33pWSYGPA","d4jBfhaKkxLGx8xLCoBrL4gHbwKOEa-5SprxKbDePWjQ_ueV9kvYgxCYnvzrnBt3cZYZ7n6UcjG8Tw","9UjXO0DX5rFgcw0cxdjrHNmsDB9-DUqo1BPrZFoDkGaxWdZ4iSrgFDdge5QXmX6KdQzzeUvmJMVDBg","hyABV_8PhuV-sZhNZdQU8n_x3W_psoxtbG1ORjDBCjEqyAccAshPzGp-14O1HFaORZvDP-Fcb0GKmg","LwbnMHSpYQvvsGEjz_MMsJIX-DBg1yFaAdDC8bV-lnKNPyg8eRSgB2a7xgrksP5-vi6WXbh9Ijmzew","ivSKQjxSZA6gZvS2BIDZYVXUmBf8NKkoEAatfCFzXswSQKmyOq_CMuwYCw1L9rRbEmJKO7knz5UpfQ","BYmN-uvrxzQhrRxtdBSMeuqfsaatwrR9xjjXQNEbuFH1SdIE7RR_dSgUFPGjLcLzQZf7w_DcFzwCWA","4N58newygntP4-ww9b-0r-H4qzxUO9SfzyQ-SrAv-Km9zGcGu-2zzTdaCmUAV66OK49nRLbB54N8XA","4098qF-YdL2oF6KZ6CfLLSZOq7huhopT3yWVUX7-F6bbKOKhnfippk5Ugf6CwCo2vm9SQPulokScQQ"]},"info":{"endOfGameResult":"GameComplete","gameCreation":1771693571185,"gameDuration":1910,"gameEndTimestamp":1771695502983,"gameId":7744691005,"gameMode":"CLASSIC","gameName":"teambuilder-match-7744691005","gameStartTimestamp":1771693596674,"gameType":"MATCHED_GAME","gameVersion":"16.4.748.682","mapId":11,"participants":[{"PlayerBehavior":{"PlayerBehavior_IsHeroInCombat":0},"PlayerScore0":0,"PlayerScore1":0,"PlayerScore10":0,"PlayerScore11":0,"PlayerScore2":0,"PlayerScore3":0,"PlayerScore4":0,"PlayerScore5":0,"PlayerScore6":0,"PlayerScore7":0,"PlayerScore8":0,"PlayerScore9":0,"allInPings":0,"assistMePings":3,"assists":7,"baronKills":0,"basicPings":0,"challenges":{"12AssistStreakCount":0,"HealFromMapSources":50,"InfernalScalePickup":0,"SWARM_DefeatAatrox":0,"SWARM_DefeatBriar":0,"SWARM_DefeatMiniBosses":0,"SWARM_EvolveWeapon":0,"SWARM_Have3Passives":0,"SWARM_KillEnemy":0,"SWARM_PickupGold":0,"SWARM_ReachLevel50":0,"SWARM_Survive15Min":0,"SWARM_WinWith5EvolvedWeapons":0,"abilityUses":176,"acesBefore15Minutes":0,"alliedJungleMonsterKills":0,"baronTakedowns":0,"blastConeOppositeOpponentCount":0,"bountyGold":570.5146484375,"buffsStolen":0,"completeSupportQuestInTime":0,"controlWardTimeCoverageInRiverOrEnemyHalf":0.8815016953995157,"controlWardsPlaced":1,"damagePerMinute":533.080296033103,"damageTakenOnTeamPercentage":0.2494796791872262,"dancedWithRiftHerald":0,"deathsByEnemyChamps":9,"dodgeSkillShotsSmallWindow":0,"doubleAces":0,"dragonTakedowns":0,"earlyLaningPhaseGoldExpAdvantage":0,"effectiveHealAndShielding":1635.1041259765625,"elderDragonKillsWithOpposingSoul":0,"elderDragonMultikills":0,"enemyChampionImmobilizations":18,"enemyJungleMonsterKills":0,"epicMonsterKillsNearEnemyJungler":0,"epicMonsterKillsWithin30SecondsOfSpawn":0,"epicMonsterSteals":0,"epicMonsterStolenWithoutSmite":0,"firstTurretKilled":0,"fistBumpParticipation":0,"flawlessAces":0,"fullTeamTakedown":1,"gameLength":1910.5834197570002,"getTakedownsInAllLanesEarlyJungleAsLaner":0,"goldPerMinute":312.5359048937503,"hadOpenNexus":0,"immobilizeAndKillWithAlly":3,"initialBuffCount":0,"initialCrabCount":0,"jungleCsBefore10Minutes":0,"junglerTakedownsNearDamagedEpicMonster":0,"kTurretsDestroyedBeforePlatesFall":0,"kda":1.2222222222222223,"killAfterHiddenWithAlly":1,"killParticipation":0.34375,"killedChampTookFullTeamDamageSurvived":0,"killingSprees":0,"killsNearEnemyTurret":1,"killsOnOtherLanesEarlyJungleAsLaner":0,"killsOnRecentlyHealedByAramPack":0,"killsUnderOwnTurret":0,"killsWithHelpFromEpicMonster":0,"knockEnemyIntoTeamAndKill":0,"landSkillShotsEarlyGame":0,"laneMinionsFirst10Minutes":47,"laningPhaseGoldExpAdvantage":0,"legendaryCount":0,"legendaryItemUsed":[3748,3075],"lostAnInhibitor":0,"maxCsAdvantageOnLaneOpponent":7,"maxKillDeficit":0,"maxLevelLeadLaneOpponent":1,"mejaisFullStackInTime":0,"moreEnemyJungleThanOpponent":0,"multiKillOneSpell":0,"multiTurretRiftHeraldCount":0,"multikills":0,"multikillsAfterAggressiveFlash":0,"outerTurretExecutesBefore10Minutes":0,"outnumberedKills":0,"outnumberedNexusKill":0,"perfectDragonSoulsTaken":0,"perfectGame":0,"pickKillWithAlly":10,"playedChampSelectPosition":1,"poroExplosions":0,"quickCleanse":0,"quickFirstTurret":0,"quickSoloKills":0,"riftHeraldTakedowns":0,"saveAllyFromDeath":0,"scuttleCrabKills":0,"shortestTimeToAceFromFirstTakedown":34.328814878,"skillshotsDodged":6,"skillshotsHit":0,"snowballsHit":0,"soloBaronKills":0,"soloKills":1,"stealthWardsPlaced":11,"survivedSingleDigitHpCount":0,"survivedThreeImmobilizesInFight":4,"takedownOnFirstTurret":0,"takedowns":11,"takedownsAfterGainingLevelAdvantage":0,"takedownsBeforeJungleMinionSpawn":0,"takedownsFirstXMinutes":3,"takedownsInAlcove":0,"takedownsInEnemyFountain":0,"teamBaronKills":0,"teamDamagePercentage":0.12913862861394804,"teamElderDragonKills":0,"teamRiftHeraldKills":0,"tookLargeDamageSurvived":0,"turretPlatesTaken":7,"turretTakedowns":1,"turretsTakenWithRiftHerald":0,"twentyMinionsIn3SecondsCount":0,"twoWardsOneSweeperCount":0,"unseenRecalls":0,"visionScoreAdvantageLaneOpponent":-0.241152822971344,"visionScorePerMinute":0.8233689392322975,"voidMonsterKill":0,"wardTakedowns":0,"wardTakedownsBefore20M":0,"wardsGuarded":0},"champExperience":14304,"champLevel":15,"championId":98,"championName":"Shen","championTransform":0,"commandPings":0,"consumablesPurchased":4,"damageDealtToBuildings":5677,"damageDealtToEpicMonsters":179,"damageDealtToObjectives":5856,"damageDealtToTurrets":5677,"damageSelfMitigated":45860,"dangerPings":0,"deaths":9,"detectorWardsPlaced":1,"doubleKills":0,"dragonKills":0,"eligibleForProgression":true,"enemyMissingPings":0,"enemyVisionPings":0,"firstBloodAssist":false,"firstBloodKill":true,"firstTowerAssist":false,"firstTowerKill":false,"gameEndedInEarlySurrender":false,"gameEndedInSurrender":false,"getBackPings":0,"goldEarned":9952,"goldSpent":9875,"holdPings":0,"individualPosition":"TOP","inhibitorKills":0,"inhibitorTakedowns":0,"inhibitorsLost":2,"item0":1031,"item1":3748,"item2":3047,"item3":3075,"item4":3066,"item5":1028,"item6":3340,"itemsPurchased":22,"killingSprees":0,"kills":4,"lane":"JUNGLE","largestCriticalStrike":22,"largestKillingSpree":0,"largestMultiKill":1,"longestTimeSpentLiving":409,"magicDamageDealt":18551,"magicDamageDealtToChampions":6273,"magicDamageTaken":1980,"missions":{"playerScore0":0,"playerScore1":0,"playerScore2":0,"playerScore3":0,"playerScore4":0,"playerScore5":0,"playerScore6":0,"playerScore7":0,"playerScore8":0,"playerScore9":0,"playerScore10":0,"playerScore11":0},"needVisionPings":0,"neutralMinionsKilled":0,"nexusKills":0,"nexusLost":1,"nexusTakedowns":0,"objectivesStolen":0,"objectivesStolenAssists":0,"onMyWayPings":5,"participantId":1,"pentaKills":0,"perks":{"statPerks":{"defense":5001,"flex":5008,"offense":5005},"styles":[{"description":"primaryStyle","selections":[{"perk":8437,"var1":1066,"var2":634,"var3":0},{"perk":8401,"var1":1135,"var2":0,"var3":0},{"perk":8444,"var1":1701,"var2":0,"var3":0},{"perk":8453,"var1":429,"var2":1118,"var3":0}],"style":8400},{"description":"subStyle","selections":[{"perk":8126,"var1":569,"var2":0,"var3":0},{"perk":8106,"var1":4,"var2":26,"var3":0}],"style":8100}]},"physicalDamageDealt":76424,"physicalDamageDealtToChampions":9416,"physicalDamageTaken":31046,"placement":0,"playerAugment1":0,"playerAugment2":0,"playerAugment3":0,"playerAugment4":0,"playerAugment5":0,"playerAugment6":0,"playerSubteamId":0,"profileIcon":6736,"pushPings":0,"puuid":"jcW3TDS_ov7wUlBYKRZGbvecykB7ZIusAuIIddY6NE3rUun13QuyRmK9MnOYP9JeqWnyWq3J8cSKQA","quadraKills":0,"retreatPings":3,"riotIdGameName":"Tyrender","riotIdTagline":"EUW","role":"NONE","roleBoundItem":1220,"sightWardsBoughtInGame":0,"spell1Casts":106,"spell2Casts":22,"spell3Casts":43,"spell4Casts":5,"subteamPlacement":0,"summoner1Casts":4,"summoner1Id":14,"summoner2Casts":5,"summoner2Id":4,"summonerId":"j2Az7Dmk5vYuXe5-2BZecd_Iv6ICPjxUCHDdpCbut8lp23c","summonerLevel":332,"summonerName":"","teamEarlySurrendered":false,"teamId":100,"teamPosition":"TOP","timeCCingOthers":34,"timePlayed":1910,"totalAllyJungleMinionsKilled":0,"totalDamageDealt":98728,"totalDamageDealtToChampions":16974,"totalDamageShieldedOnTeammates":1635,"totalDamageTaken":36517,"totalEnemyJungleMinionsKilled":0,"totalHeal":2901,"totalHealsOnTeammates":0,"totalMinionsKilled":138,"totalTimeCCDealt":227,"totalTimeSpentDead":286,"totalUnitsHealed":1,"tripleKills":0,"trueDamageDealt":3752,"trueDamageDealtToChampions":1285,"trueDamageTaken":3490,"turretKills":1,"turretTakedowns":1,"turretsLost":11,"unrealKills":0,"visionClearedPings":0,"visionScore":26,"visionWardsBoughtInGame":1,"wardsKilled":0,"wardsPlaced":12,"win":false},{"PlayerBehavior":{"PlayerBehavior_IsHeroInCombat":0},"PlayerScore0":0,"PlayerScore1":0,"PlayerScore10":0,"PlayerScore11":0,"PlayerScore2":0,"PlayerScore3":0,"PlayerScore4":0,"PlayerScore5":0,"PlayerScore6":0,"PlayerScore7":0,"PlayerScore8":0,"PlayerScore9":0,"allInPings":0,"assistMePings":4,"assists":9,"baronKills":0,"basicPings":0,"challenges":{"12AssistStreakCount":0,"HealFromMapSources":1082,"InfernalScalePickup":0,"SWARM_DefeatAatrox":0,"SWARM_DefeatBriar":0,"SWARM_DefeatMiniBosses":0,"SWARM_EvolveWeapon":0,"SWARM_Have3Passives":0,"SWARM_KillEnemy":0,"SWARM_PickupGold":0,"SWARM_ReachLevel50":0,"SWARM_Survive15Min":0,"SWARM_WinWith5EvolvedWeapons":0,"abilityUses":392,"acesBefore15Minutes":0,"alliedJungleMonsterKills":92,"baronTakedowns":0,"blastConeOppositeOpponentCount":0,"bountyGold":0,"buffsStolen":1,"completeSupportQuestInTime":0,"controlWardTimeCoverageInRiverOrEnemyHalf":0.588446941958699,"controlWardsPlaced":1,"damagePerMinute":679.0943912514533,"damageTakenOnTeamPercentage":0.20146919276472394,"dancedWithRiftHerald":0,"deathsByEnemyChamps":6,"dodgeSkillShotsSmallWindow":0,"doubleAces":0,"dragonTakedowns":0,"earlyLaningPhaseGoldExpAdvantage":0,"effectiveHealAndShielding":0,"elderDragonKillsWithOpposingSoul":0,"elderDragonMultikills":0,"enemyChampionImmobilizations":0,"enemyJungleMonsterKills":9,"epicMonsterKillsNearEnemyJungler":1,"epicMonsterKillsWithin30SecondsOfSpawn":0,"epicMonsterSteals":0,"epicMonsterStolenWithoutSmite":0,"firstTurretKilled":0,"fistBumpParticipation":0,"flawlessAces":0,"fullTeamTakedown":1,"gameLength":1910.5834197570002,"goldPerMinute":376.53328022651715,"hadOpenNexus":0,"immobilizeAndKillWithAlly":0,"initialBuffCount":2,"initialCrabCount":0,"jungleCsBefore10Minutes":52.000000059604645,"junglerKillsEarlyJungle":1,"junglerTakedownsNearDamagedEpicMonster":0,"kTurretsDestroyedBeforePlatesFall":0,"kda":2.1666666666666665,"killAfterHiddenWithAlly":1,"killParticipation":0.40625,"killedChampTookFullTeamDamageSurvived":0,"killingSprees":0,"killsNearEnemyTurret":0,"killsOnLanersEarlyJungleAsJungler":0,"killsOnRecentlyHealedByAramPack":0,"killsUnderOwnTurret":3,"killsWithHelpFromEpicMonster":0,"knockEnemyIntoTeamAndKill":0,"landSkillShotsEarlyGame":3,"laneMinionsFirst10Minutes":1,"laningPhaseGoldExpAdvantage":0,"legendaryCount":0,"legendaryItemUsed":[6692,3071,3814],"lostAnInhibitor":0,"maxCsAdvantageOnLaneOpponent":12.150000005960464,"maxKillDeficit":0,"maxLevelLeadLaneOpponent":1,"mejaisFullStackInTime":0,"moreEnemyJungleThanOpponent":-26.500000059604645,"multiKillOneSpell":0,"multiTurretRiftHeraldCount":0,"multikills":0,"multikillsAfterAggressiveFlash":0,"outerTurretExecutesBefore10Minutes":0,"outnumberedKills":1,"outnumberedNexusKill":0,"perfectDragonSoulsTaken":0,"perfectGame":0,"pickKillWithAlly":10,"playedChampSelectPosition":1,"poroExplosions":0,"quickCleanse":0,"quickFirstTurret":0,"quickSoloKills":0,"riftHeraldTakedowns":0,"saveAllyFromDeath":0,"scuttleCrabKills":1,"shortestTimeToAceFromFirstTakedown":34.328814878,"skillshotsDodged":11,"skillshotsHit":46,"snowballsHit":0,"soloBaronKills":0,"soloKills":2,"stealthWardsPlaced":4,"survivedSingleDigitHpCount":0,"survivedThreeImmobilizesInFight":0,"takedownOnFirstTurret":0,"takedowns":13,"takedownsAfterGainingLevelAdvantage":0,"takedownsBeforeJungleMinionSpawn":0,"takedownsFirstXMinutes":4,"takedownsInAlcove":0,"takedownsInEnemyFountain":0,"teamBaronKills":0,"teamDamagePercentage":0.16451052315801737,"teamElderDragonKills":0,"teamRiftHeraldKills":0,"tookLargeDamageSurvived":0,"turretPlatesTaken":2,"turretTakedowns":0,"turretsTakenWithRiftHerald":0,"twentyMinionsIn3SecondsCount":0,"twoWardsOneSweeperCount":2,"unseenRecalls":0,"visionScoreAdvantageLaneOpponent":-0.4225885272026062,"visionScorePerMinute":0.772865590889819,"voidMonsterKill":2,"wardTakedowns":3,"wardTakedownsBefore20M":3,"wardsGuarded":0},"champExperience":14982,"champLevel":16,"championId":238,"championName":"Zed","championTransform":0,"commandPings":4,"consumablesPurchased":3,"damageDealtToBuildings":568,"damageDealtToEpicMonsters":7038,"damageDealtToObjectives":7607,"damageDealtToTurrets":568,"damageSelfMitigated":23726,"dangerPings":0,"deaths":6,"detectorWardsPlaced":2,"doubleKills":0,"dragonKills":0,"eligibleForProgression":true,"enemyMissingPings":1,"enemyVisionPings":9,"firstBloodAssist":false,"firstBloodKill":false,"firstTowerAssist":false,"firstTowerKill":false,"gameEndedInEarlySurrender":false,"gameEndedInSurrender":false,"getBackPings":16,"goldEarned":11989,"goldSpent":11625,"holdPings":0,"individualPosition":"JUNGLE","inhibitorKills":0,"inhibitorTakedowns":0,"inhibitorsLost":2,"item0":3047,"item1":1037,"item2":3814,"item3":0,"item4":6692,"item5":3071,"item6":3364,"itemsPurchased":29,"killingSprees":1,"kills":4,"lane":"JUNGLE","largestCriticalStrike":0,"largestKillingSpree":2,"largestMultiKill":1,"longestTimeSpentLiving":798,"magicDamageDealt":18544,"magicDamageDealtToChampions":1148,"magicDamageTaken":1953,"missions":{"playerScore0":0,"playerScore1":0,"playerScore2":0,"playerScore3":0,"playerScore4":0,"playerScore5":0,"playerScore6":0,"playerScore7":0,"playerScore8":0,"playerScore9":0,"playerScore10":0,"playerScore11":0},"needVisionPings":2,"neutralMinionsKilled":162,"nexusKills":0,"nexusLost":1,"nexusTakedowns":0,"objectivesStolen":0,"objectivesStolenAssists":0,"onMyWayPings":14,"participantId":2,"pentaKills":0,"perks":{"statPerks":{"defense":5001,"flex":5008,"offense":5008},"styles":[{"description":"primaryStyle","selections":[{"perk":8112,"var1":1716,"var2":0,"var3":0},{"perk":8143,"var1":824,"var2":0,"var3":0},{"perk":8140,"var1":13,"var2":0,"var3":0},{"perk":8106,"var1":5,"var2":31,"var3":0}],"style":8100},{"description":"subStyle","selections":[{"perk":8014,"var1":473,"var2":0,"var3":0},{"perk":9111,"var1":751,"var2":260,"var3":0}],"style":8000}]},"physicalDamageDealt":141845,"physicalDamageDealtToChampions":19263,"physicalDamageTaken":25286,"placement":0,"playerAugment1":0,"playerAugment2":0,"playerAugment3":0,"playerAugment4":0,"playerAugment5":0,"playerAugment6":0,"playerSubteamId":0,"profileIcon":6892,"pushPings":1,"puuid":"RunCLgHixgLPXO6tjcGx4ku64FI3oXN6ECqBo80X2r7As0h69v5GYjnJqR-5H6ccHV8QU33pWSYGPA","quadraKills":0,"retreatPings":0,"riotIdGameName":"IIIEUPHONIII","riotIdTagline":"EUW","role":"NONE","roleBoundItem":1209,"sightWardsBoughtInGame":0,"spell1Casts":133,"spell2Casts":84,"spell3Casts":159,"spell4Casts":16,"subteamPlacement":0,"summoner1Casts":18,"summoner1Id":11,"summoner2Casts":2,"summoner2Id":4,"summonerId":"vlKb1RvEq6h7Q2rWLrqkpXbDq1mq6ZaecuLTHCuuVn-boMM","summonerLevel":435,"summonerName":"","teamEarlySurrendered":false,"teamId":100,"teamPosition":"JUNGLE","timeCCingOthers":10,"timePlayed":1906,"totalAllyJungleMinionsKilled":132,"totalDamageDealt":256605,"totalDamageDealtToChampions":21624,"totalDamageShieldedOnTeammates":0,"totalDamageTaken":29490,"totalEnemyJungleMinionsKilled":10,"totalHeal":9335,"totalHealsOnTeammates":0,"totalMinionsKilled":34,"totalTimeCCDealt":315,"totalTimeSpentDead":186,"totalUnitsHealed":1,"tripleKills":0,"trueDamageDealt":96214,"trueDamageDealtToChampions":1212,"trueDamageTaken":2249,"turretKills":0,"turretTakedowns":0,"turretsLost":11,"unrealKills":0,"visionClearedPings":0,"visionScore":24,"visionWardsBoughtInGame":2,"wardsKilled":3,"wardsPlaced":6,"win":false},{"PlayerBehavior":{"PlayerBehavior_IsHeroInCombat":0},"PlayerScore0":0,"PlayerScore1":0,"PlayerScore10":0,"PlayerScore11":0,"PlayerScore2":0,"PlayerScore3":0,"PlayerScore4":0,"PlayerScore5":0,"PlayerScore6":0,"PlayerScore7":0,"PlayerScore8":0,"PlayerScore9":0,"allInPings":3,"assistMePings":5,"assists":4,"baronKills":0,"basicPings":0,"challenges":{"12AssistStreakCount":0,"HealFromMapSources":0,"InfernalScalePickup":0,"SWARM_DefeatAatrox":0,"SWARM_DefeatBriar":0,"SWARM_DefeatMiniBosses":0,"SWARM_EvolveWeapon":0,"SWARM_Have3Passives":0,"SWARM_KillEnemy":0,"SWARM_PickupGold":0,"SWARM_ReachLevel50":0,"SWARM_Survive15Min":0,"SWARM_WinWith5EvolvedWeapons":0,"abilityUses":214,"acesBefore15Minutes":0,"alliedJungleMonsterKills":0,"baronTakedowns":0,"blastConeOppositeOpponentCount":0,"bountyGold":1170.9593505859375,"buffsStolen":0,"completeSupportQuestInTime":0,"controlWardsPlaced":1,"damagePerMinute":1236.3649831109894,"damageTakenOnTeamPercentage":0.16066975636309855,"dancedWithRiftHerald":0,"deathsByEnemyChamps":8,"dodgeSkillShotsSmallWindow":0,"doubleAces":0,"dragonTakedowns":0,"earlyLaningPhaseGoldExpAdvantage":1,"effectiveHealAndShielding":0,"elderDragonKillsWithOpposingSoul":0,"elderDragonMultikills":0,"enemyChampionImmobilizations":22,"enemyJungleMonsterKills":0,"epicMonsterKillsNearEnemyJungler":0,"epicMonsterKillsWithin30SecondsOfSpawn":0,"epicMonsterSteals":0,"epicMonsterStolenWithoutSmite":0,"fastestLegendary":1583.629761933,"firstTurretKilled":0,"fistBumpParticipation":0,"flawlessAces":0,"fullTeamTakedown":1,"gameLength":1910.5834197570002,"getTakedownsInAllLanesEarlyJungleAsLaner":0,"goldPerMinute":438.26990346435616,"hadOpenNexus":0,"immobilizeAndKillWithAlly":6,"initialBuffCount":0,"initialCrabCount":0,"jungleCsBefore10Minutes":0,"junglerTakedownsNearDamagedEpicMonster":0,"kTurretsDestroyedBeforePlatesFall":0,"kda":2,"killAfterHiddenWithAlly":3,"killParticipation":0.5,"killedChampTookFullTeamDamageSurvived":0,"killingSprees":1,"killsNearEnemyTurret":1,"killsOnOtherLanesEarlyJungleAsLaner":0,"killsOnRecentlyHealedByAramPack":0,"killsUnderOwnTurret":2,"killsWithHelpFromEpicMonster":1,"knockEnemyIntoTeamAndKill":0,"landSkillShotsEarlyGame":36,"laneMinionsFirst10Minutes":65,"laningPhaseGoldExpAdvantage":1,"legendaryCount":1,"legendaryItemUsed":[6655,4645,3089],"lostAnInhibitor":0,"maxCsAdvantageOnLaneOpponent":50,"maxKillDeficit":0,"maxLevelLeadLaneOpponent":2,"mejaisFullStackInTime":0,"moreEnemyJungleThanOpponent":0,"multiKillOneSpell":0,"multiTurretRiftHeraldCount":0,"multikills":3,"multikillsAfterAggressiveFlash":0,"outerTurretExecutesBefore10Minutes":0,"outnumberedKills":0,"outnumberedNexusKill":0,"perfectDragonSoulsTaken":0,"perfectGame":0,"pickKillWithAlly":11,"playedChampSelectPosition":1,"poroExplosions":0,"quickCleanse":0,"quickFirstTurret":0,"quickSoloKills":0,"riftHeraldTakedowns":0,"saveAllyFromDeath":0,"scuttleCrabKills":0,"shortestTimeToAceFromFirstTakedown":34.328814878,"skillshotsDodged":14,"skillshotsHit":261,"snowballsHit":0,"soloBaronKills":0,"soloKills":4,"stealthWardsPlaced":10,"survivedSingleDigitHpCount":0,"survivedThreeImmobilizesInFight":2,"takedownOnFirstTurret":0,"takedowns":16,"takedownsAfterGainingLevelAdvantage":0,"takedownsBeforeJungleMinionSpawn":0,"takedownsFirstXMinutes":4,"takedownsInAlcove":0,"takedownsInEnemyFountain":0,"teamBaronKills":0,"teamDamagePercentage":0.29950924761875936,"teamElderDragonKills":0,"teamRiftHeraldKills":0,"tookLargeDamageSurvived":0,"turretPlatesTaken":6,"turretTakedowns":1,"turretsTakenWithRiftHerald":0,"twentyMinionsIn3SecondsCount":0,"twoWardsOneSweeperCount":0,"unseenRecalls":0,"visionScoreAdvantageLaneOpponent":1.168818712234497,"visionScorePerMinute":1.1704634208829867,"voidMonsterKill":0,"wardTakedowns":4,"wardTakedownsBefore20M":2,"wardsGuarded":1},"champExperience":14714,"champLevel":16,"championId":800,"championName":"Mel","championTransform":0,"commandPings":7,"consumablesPurchased":7,"damageDealtToBuildings":7676,"damageDealtToEpicMonsters":58,"damageDealtToObjectives":7735,"damageDealtToTurrets":7676,"damageSelfMitigated":16407,"dangerPings":0,"deaths":8,"detectorWardsPlaced":1,"doubleKills":2,"dragonKills":0,"eligibleForProgression":true,"enemyMissingPings":9,"enemyVisionPings":0,"firstBloodAssist":false,"firstBloodKill":false,"firstTowerAssist":false,"firstTowerKill":false,"gameEndedInEarlySurrender":false,"gameEndedInSurrender":false,"getBackPings":0,"goldEarned":13955,"goldSpent":12925,"holdPings":0,"individualPosition":"MIDDLE","inhibitorKills":0,"inhibitorTakedowns":0,"inhibitorsLost":2,"item0":1056,"item1":2421,"item2":3175,"item3":4645,"item4":3089,"item5":6655,"item6":3340,"itemsPurchased":23,"killingSprees":2,"kills":12,"lane":"MIDDLE","largestCriticalStrike":450,"largestKillingSpree":8,"largestMultiKill":3,"longestTimeSpentLiving":514,"magicDamageDealt":102760,"magicDamageDealtToChampions":35971,"magicDamageTaken":1701,"missions":{"playerScore0":0,"playerScore1":0,"playerScore2":0,"playerScore3":0,"playerScore4":0,"playerScore5":0,"playerScore6":0,"playerScore7":0,"playerScore8":0,"playerScore9":0,"playerScore10":0,"playerScore11":0},"needVisionPings":0,"neutralMinionsKilled":0,"nexusKills":0,"nexusLost":1,"nexusTakedowns":0,"objectivesStolen":0,"objectivesStolenAssists":0,"onMyWayPings":4,"participantId":3,"pentaKills":0,"perks":{"statPerks":{"defense":5001,"flex":5008,"offense":5007},"styles":[{"description":"primaryStyle","selections":[{"perk":8229,"var1":3024,"var2":0,"var3":0},{"perk":8226,"var1":250,"var2":868,"var3":0},{"perk":8210,"var1":32,"var2":0,"var3":0},{"perk":8237,"var1":1126,"var2":0,"var3":0}],"style":8200},{"description":"subStyle","selections":[{"perk":8014,"var1":1038,"var2":0,"var3":0},{"perk":8009,"var1":3621,"var2":0,"var3":0}],"style":8000}]},"physicalDamageDealt":15997,"physicalDamageDealtToChampions":3252,"physicalDamageTaken":19391,"placement":0,"playerAugment1":0,"playerAugment2":0,"playerAugment3":0,"playerAugment4":0,"playerAugment5":0,"playerAugment6":0,"playerSubteamId":0,"profileIcon":6255,"pushPings":0,"puuid":"d4jBfhaKkxLGx8xLCoBrL4gHbwKOEa-5SprxKbDePWjQ_ueV9kvYgxCYnvzrnBt3cZYZ7n6UcjG8Tw","quadraKills":0,"retreatPings":4,"riotIdGameName":"Larscoste17","riotIdTagline":"EUW","role":"SOLO","roleBoundItem":1206,"sightWardsBoughtInGame":0,"spell1Casts":122,"spell2Casts":23,"spell3Casts":62,"spell4Casts":7,"subteamPlacement":0,"summoner1Casts":2,"summoner1Id":12,"summoner2Casts":5,"summoner2Id":4,"summonerId":"KrAbRLtHvUJ-IfNTSZRLoPrIlk2Z9tIVVLSF6OB80JurpHE","summonerLevel":429,"summonerName":"","teamEarlySurrendered":false,"teamId":100,"teamPosition":"MIDDLE","timeCCingOthers":39,"timePlayed":1910,"totalAllyJungleMinionsKilled":0,"totalDamageDealt":122290,"totalDamageDealtToChampions":39369,"totalDamageShieldedOnTeammates":0,"totalDamageTaken":23518,"totalEnemyJungleMinionsKilled":0,"totalHeal":1553,"totalHealsOnTeammates":0,"totalMinionsKilled":195,"totalTimeCCDealt":276,"totalTimeSpentDead":279,"totalUnitsHealed":1,"tripleKills":1,"trueDamageDealt":3532,"trueDamageDealtToChampions":145,"trueDamageTaken":2425,"turretKills":1,"turretTakedowns":1,"turretsLost":11,"unrealKills":0,"visionClearedPings":0,"visionScore":37,"visionWardsBoughtInGame":1,"wardsKilled":4,"wardsPlaced":11,"win":false},{"PlayerBehavior":{"PlayerBehavior_IsHeroInCombat":0},"PlayerScore0":0,"PlayerScore1":0,"PlayerScore10":0,"PlayerScore11":0,"PlayerScore2":0,"PlayerScore3":0,"PlayerScore4":0,"PlayerScore5":0,"PlayerScore6":0,"PlayerScore7":0,"PlayerScore8":0,"PlayerScore9":0,"allInPings":0,"assistMePings":9,"assists":11,"baronKills":0,"basicPings":0,"challenges":{"12AssistStreakCount":0,"HealFromMapSources":0,"InfernalScalePickup":0,"SWARM_DefeatAatrox":0,"SWARM_DefeatBriar":0,"SWARM_DefeatMiniBosses":0,"SWARM_EvolveWeapon":0,"SWARM_Have3Passives":0,"SWARM_KillEnemy":0,"SWARM_PickupGold":0,"SWARM_ReachLevel50":0,"SWARM_Survive15Min":0,"SWARM_WinWith5EvolvedWeapons":0,"abilityUses":194,"acesBefore15Minutes":0,"alliedJungleMonsterKills":0,"baronTakedowns":0,"blastConeOppositeOpponentCount":0,"bountyGold":116.01762390136719,"buffsStolen":0,"completeSupportQuestInTime":0,"controlWardTimeCoverageInRiverOrEnemyHalf":0.44003215880672086,"controlWardsPlaced":1,"damagePerMinute":728.2831457325075,"damageTakenOnTeamPercentage":0.1880872539907986,"dancedWithRiftHerald":0,"deathsByEnemyChamps":10,"dodgeSkillShotsSmallWindow":0,"doubleAces":0,"dragonTakedowns":0,"earlyLaningPhaseGoldExpAdvantage":0,"effectiveHealAndShielding":0,"elderDragonKillsWithOpposingSoul":0,"elderDragonMultikills":0,"enemyChampionImmobilizations":0,"enemyJungleMonsterKills":0,"epicMonsterKillsNearEnemyJungler":0,"epicMonsterKillsWithin30SecondsOfSpawn":0,"epicMonsterSteals":0,"epicMonsterStolenWithoutSmite":0,"firstTurretKilled":0,"fistBumpParticipation":0,"flawlessAces":0,"fullTeamTakedown":1,"gameLength":1910.5834197570002,"getTakedownsInAllLanesEarlyJungleAsLaner":0,"goldPerMinute":452.7213035881266,"hadOpenNexus":0,"immobilizeAndKillWithAlly":0,"initialBuffCount":0,"initialCrabCount":0,"jungleCsBefore10Minutes":0,"junglerTakedownsNearDamagedEpicMonster":0,"kTurretsDestroyedBeforePlatesFall":0,"kda":1.9,"killAfterHiddenWithAlly":2,"killParticipation":0.59375,"killedChampTookFullTeamDamageSurvived":0,"killingSprees":0,"killsNearEnemyTurret":0,"killsOnOtherLanesEarlyJungleAsLaner":0,"killsOnRecentlyHealedByAramPack":0,"killsUnderOwnTurret":2,"killsWithHelpFromEpicMonster":0,"knockEnemyIntoTeamAndKill":0,"landSkillShotsEarlyGame":1,"laneMinionsFirst10Minutes":56,"laningPhaseGoldExpAdvantage":0,"legendaryCount":0,"legendaryItemUsed":[3072,6676,3031],"lostAnInhibitor":0,"maxCsAdvantageOnLaneOpponent":8,"maxKillDeficit":0,"maxLevelLeadLaneOpponent":0,"mejaisFullStackInTime":0,"moreEnemyJungleThanOpponent":0,"multiKillOneSpell":0,"multiTurretRiftHeraldCount":0,"multikills":1,"multikillsAfterAggressiveFlash":0,"outerTurretExecutesBefore10Minutes":0,"outnumberedKills":0,"outnumberedNexusKill":0,"perfectDragonSoulsTaken":0,"perfectGame":0,"pickKillWithAlly":16,"playedChampSelectPosition":1,"poroExplosions":0,"quickCleanse":0,"quickFirstTurret":0,"quickSoloKills":0,"riftHeraldTakedowns":0,"saveAllyFromDeath":0,"scuttleCrabKills":0,"shortestTimeToAceFromFirstTakedown":34.328814878,"skillshotsDodged":14,"skillshotsHit":83,"snowballsHit":0,"soloBaronKills":0,"soloKills":0,"stealthWardsPlaced":3,"survivedSingleDigitHpCount":0,"survivedThreeImmobilizesInFight":9,"takedownOnFirstTurret":0,"takedowns":19,"takedownsAfterGainingLevelAdvantage":0,"takedownsBeforeJungleMinionSpawn":0,"takedownsFirstXMinutes":9,"takedownsInAlcove":0,"takedownsInEnemyFountain":0,"teamBaronKills":0,"teamDamagePercentage":0.17642649218591233,"teamElderDragonKills":0,"teamRiftHeraldKills":0,"tookLargeDamageSurvived":0,"turretPlatesTaken":5,"turretTakedowns":1,"turretsTakenWithRiftHerald":0,"twentyMinionsIn3SecondsCount":0,"twoWardsOneSweeperCount":0,"unseenRecalls":0,"visionScoreAdvantageLaneOpponent":-0.43371522426605225,"visionScorePerMinute":0.3454807584606343,"voidMonsterKill":0,"wardTakedowns":1,"wardTakedownsBefore20M":0,"wardsGuarded":1},"champExperience":11974,"champLevel":14,"championId":21,"championName":"MissFortune","championTransform":0,"commandPings":8,"consumablesPurchased":3,"damageDealtToBuildings":6799,"damageDealtToEpicMonsters":0,"damageDealtToObjectives":6799,"damageDealtToTurrets":6799,"damageSelfMitigated":16954,"dangerPings":0,"deaths":10,"detectorWardsPlaced":1,"doubleKills":1,"dragonKills":0,"eligibleForProgression":true,"enemyMissingPings":1,"enemyVisionPings":0,"firstBloodAssist":false,"firstBloodKill":false,"firstTowerAssist":false,"firstTowerKill":false,"gameEndedInEarlySurrender":false,"gameEndedInSurrender":false,"getBackPings":0,"goldEarned":14416,"goldSpent":14300,"holdPings":0,"individualPosition":"BOTTOM","inhibitorKills":0,"inhibitorTakedowns":0,"inhibitorsLost":2,"item0":2055,"item1":3072,"item2":6676,"item3":6670,"item4":3035,"item5":3031,"item6":3363,"itemsPurchased":23,"killingSprees":2,"kills":8,"lane":"BOTTOM","largestCriticalStrike":808,"largestKillingSpree":2,"largestMultiKill":2,"longestTimeSpentLiving":481,"magicDamageDealt":4860,"magicDamageDealtToChampions":931,"magicDamageTaken":2938,"missions":{"playerScore0":0,"playerScore1":0,"playerScore2":0,"playerScore3":0,"playerScore4":0,"playerScore5":0,"playerScore6":0,"playerScore7":0,"playerScore8":0,"playerScore9":0,"playerScore10":0,"playerScore11":0},"needVisionPings":0,"neutralMinionsKilled":0,"nexusKills":0,"nexusLost":1,"nexusTakedowns":0,"objectivesStolen":0,"objectivesStolenAssists":0,"onMyWayPings":2,"participantId":4,"pentaKills":0,"perks":{"statPerks":{"defense":5011,"flex":5008,"offense":5008},"styles":[{"description":"primaryStyle","selections":[{"perk":8369,"var1":796,"var2":498,"var3":0},{"perk":8321,"var1":742,"var2":0,"var3":0},{"perk":8345,"var1":3,"var2":0,"var3":160},{"perk":8347,"var1":0,"var2":0,"var3":0}],"style":8300},{"description":"subStyle","selections":[{"perk":8236,"var1":28,"var2":0,"var3":0},{"perk":8226,"var1":250,"var2":637,"var3":0}],"style":8200}]},"physicalDamageDealt":111383,"physicalDamageDealtToChampions":21127,"physicalDamageTaken":22206,"placement":0,"playerAugment1":0,"playerAugment2":0,"playerAugment3":0,"playerAugment4":0,"playerAugment5":0,"playerAugment6":0,"playerSubteamId":0,"profileIcon":3006,"pushPings":0,"puuid":"9UjXO0DX5rFgcw0cxdjrHNmsDB9-DUqo1BPrZFoDkGaxWdZ4iSrgFDdge5QXmX6KdQzzeUvmJMVDBg","quadraKills":0,"retreatPings":0,"riotIdGameName":"Kringord","riotIdTagline":"EUW","role":"CARRY","roleBoundItem":3009,"sightWardsBoughtInGame":0,"spell1Casts":104,"spell2Casts":43,"spell3Casts":40,"spell4Casts":7,"subteamPlacement":0,"summoner1Casts":5,"summoner1Id":4,"summoner2Casts":7,"summoner2Id":21,"summonerId":"ZOn_WCjT_ARajcqhIA1bZ_NF856wuKSVehuZMMrRv0WwSmVq","summonerLevel":390,"summonerName":"","teamEarlySurrendered":false,"teamId":100,"teamPosition":"BOTTOM","timeCCingOthers":9,"timePlayed":1910,"totalAllyJungleMinionsKilled":0,"totalDamageDealt":121672,"totalDamageDealtToChampions":23190,"totalDamageShieldedOnTeammates":0,"totalDamageTaken":27531,"totalEnemyJungleMinionsKilled":0,"totalHeal":5317,"totalHealsOnTeammates":0,"totalMinionsKilled":185,"totalTimeCCDealt":175,"totalTimeSpentDead":339,"totalUnitsHealed":1,"tripleKills":0,"trueDamageDealt":5428,"trueDamageDealtToChampions":1131,"trueDamageTaken":2385,"turretKills":1,"turretTakedowns":1,"turretsLost":11,"unrealKills":0,"visionClearedPings":0,"visionScore":11,"visionWardsBoughtInGame":2,"wardsKilled":1,"wardsPlaced":6,"win":false},{"PlayerBehavior":{"PlayerBehavior_IsHeroInCombat":0},"PlayerScore0":0,"PlayerScore1":0,"PlayerScore10":0,"PlayerScore11":0,"PlayerScore2":0,"PlayerScore3":0,"PlayerScore4":0,"PlayerScore5":0,"PlayerScore6":0,"PlayerScore7":0,"PlayerScore8":0,"PlayerScore9":0,"allInPings":5,"assistMePings":4,"assists":13,"baronKills":0,"basicPings":0,"challenges":{"12AssistStreakCount":0,"HealFromMapSources":0,"InfernalScalePickup":0,"SWARM_DefeatAatrox":0,"SWARM_DefeatBriar":0,"SWARM_DefeatMiniBosses":0,"SWARM_EvolveWeapon":0,"SWARM_Have3Passives":0,"SWARM_KillEnemy":0,"SWARM_PickupGold":0,"SWARM_ReachLevel50":0,"SWARM_Survive15Min":0,"SWARM_WinWith5EvolvedWeapons":0,"abilityUses":189,"acesBefore15Minutes":0,"alliedJungleMonsterKills":0,"baronTakedowns":0,"blastConeOppositeOpponentCount":0,"bountyGold":0,"buffsStolen":0,"completeSupportQuestInTime":1,"controlWardsPlaced":0,"damagePerMinute":951.1464968086179,"damageTakenOnTeamPercentage":0.20029411769415273,"dancedWithRiftHerald":0,"deathsByEnemyChamps":14,"dodgeSkillShotsSmallWindow":0,"doubleAces":0,"dragonTakedowns":0,"earlyLaningPhaseGoldExpAdvantage":0,"effectiveHealAndShielding":683.6792602539062,"elderDragonKillsWithOpposingSoul":0,"elderDragonMultikills":0,"enemyChampionImmobilizations":20,"enemyJungleMonsterKills":0,"epicMonsterKillsNearEnemyJungler":0,"epicMonsterKillsWithin30SecondsOfSpawn":0,"epicMonsterSteals":0,"epicMonsterStolenWithoutSmite":0,"firstTurretKilled":0,"fistBumpParticipation":0,"flawlessAces":0,"fullTeamTakedown":1,"gameLength":1910.5834197570002,"getTakedownsInAllLanesEarlyJungleAsLaner":0,"goldPerMinute":297.5027330315643,"hadOpenNexus":0,"immobilizeAndKillWithAlly":4,"initialBuffCount":0,"initialCrabCount":0,"jungleCsBefore10Minutes":0,"junglerTakedownsNearDamagedEpicMonster":0,"kTurretsDestroyedBeforePlatesFall":0,"kda":1.2142857142857142,"killAfterHiddenWithAlly":1,"killParticipation":0.53125,"killedChampTookFullTeamDamageSurvived":0,"killingSprees":0,"killsNearEnemyTurret":0,"killsOnOtherLanesEarlyJungleAsLaner":0,"killsOnRecentlyHealedByAramPack":0,"killsUnderOwnTurret":1,"killsWithHelpFromEpicMonster":0,"knockEnemyIntoTeamAndKill":4,"landSkillShotsEarlyGame":16,"laneMinionsFirst10Minutes":14,"laningPhaseGoldExpAdvantage":0,"legendaryCount":0,"legendaryItemUsed":[6655,3871,4628],"lostAnInhibitor":0,"maxCsAdvantageOnLaneOpponent":23,"maxKillDeficit":0,"maxLevelLeadLaneOpponent":1,"mejaisFullStackInTime":0,"moreEnemyJungleThanOpponent":0,"multiKillOneSpell":0,"multiTurretRiftHeraldCount":0,"multikills":0,"multikillsAfterAggressiveFlash":0,"outerTurretExecutesBefore10Minutes":0,"outnumberedKills":0,"outnumberedNexusKill":0,"perfectDragonSoulsTaken":0,"perfectGame":0,"pickKillWithAlly":14,"playedChampSelectPosition":1,"poroExplosions":0,"quickCleanse":0,"quickFirstTurret":0,"quickSoloKills":0,"riftHeraldTakedowns":0,"saveAllyFromDeath":0,"scuttleCrabKills":0,"shortestTimeToAceFromFirstTakedown":34.328814878,"skillshotsDodged":8,"skillshotsHit":113,"snowballsHit":0,"soloBaronKills":0,"soloKills":0,"stealthWardsPlaced":21,"survivedSingleDigitHpCount":0,"survivedThreeImmobilizesInFight":10,"takedownOnFirstTurret":0,"takedowns":17,"takedownsAfterGainingLevelAdvantage":0,"takedownsBeforeJungleMinionSpawn":0,"takedownsFirstXMinutes":9,"takedownsInAlcove":1,"takedownsInEnemyFountain":0,"teamBaronKills":0,"teamDamagePercentage":0.2304151084233629,"teamElderDragonKills":0,"teamRiftHeraldKills":0,"tookLargeDamageSurvived":0,"turretPlatesTaken":2,"turretTakedowns":0,"turretsTakenWithRiftHerald":0,"twentyMinionsIn3SecondsCount":0,"twoWardsOneSweeperCount":0,"unseenRecalls":0,"visionScoreAdvantageLaneOpponent":-0.0886881947517395,"visionScorePerMinute":1.8428389389145152,"voidMonsterKill":0,"wardTakedowns":5,"wardTakedownsBefore20M":2,"wardsGuarded":0},"champExperience":11058,"champLevel":13,"championId":161,"championName":"Velkoz","championTransform":0,"commandPings":7,"consumablesPurchased":3,"damageDealtToBuildings":484,"damageDealtToEpicMonsters":223,"damageDealtToObjectives":707,"damageDealtToTurrets":484,"damageSelfMitigated":11262,"dangerPings":0,"deaths":14,"detectorWardsPlaced":0,"doubleKills":0,"dragonKills":0,"eligibleForProgression":true,"enemyMissingPings":1,"enemyVisionPings":3,"firstBloodAssist":false,"firstBloodKill":false,"firstTowerAssist":false,"firstTowerKill":false,"gameEndedInEarlySurrender":false,"gameEndedInSurrender":false,"getBackPings":7,"goldEarned":9473,"goldSpent":8190,"holdPings":0,"individualPosition":"UTILITY","inhibitorKills":0,"inhibitorTakedowns":0,"inhibitorsLost":2,"item0":3871,"item1":6655,"item2":3020,"item3":4628,"item4":3145,"item5":0,"item6":3364,"itemsPurchased":26,"killingSprees":1,"kills":4,"lane":"BOTTOM","largestCriticalStrike":0,"largestKillingSpree":2,"largestMultiKill":1,"longestTimeSpentLiving":248,"magicDamageDealt":39001,"magicDamageDealtToChampions":21421,"magicDamageTaken":2905,"missions":{"playerScore0":0,"playerScore1":0,"playerScore2":0,"playerScore3":0,"playerScore4":0,"playerScore5":0,"playerScore6":0,"playerScore7":0,"playerScore8":0,"playerScore9":0,"playerScore10":0,"playerScore11":0},"needVisionPings":0,"neutralMinionsKilled":0,"nexusKills":0,"nexusLost":1,"nexusTakedowns":0,"objectivesStolen":0,"objectivesStolenAssists":0,"onMyWayPings":0,"participantId":5,"pentaKills":0,"perks":{"statPerks":{"defense":5001,"flex":5008,"offense":5008},"styles":[{"description":"primaryStyle","selections":[{"perk":8229,"var1":1638,"var2":0,"var3":0},{"perk":8226,"var1":250,"var2":504,"var3":0},{"perk":8210,"var1":13,"var2":0,"var3":0},{"perk":8237,"var1":619,"var2":0,"var3":0}],"style":8200},{"description":"subStyle","selections":[{"perk":8126,"var1":716,"var2":0,"var3":0},{"perk":8106,"var1":5,"var2":31,"var3":0}],"style":8100}]},"physicalDamageDealt":3628,"physicalDamageDealtToChampions":515,"physicalDamageTaken":24269,"placement":0,"playerAugment1":0,"playerAugment2":0,"playerAugment3":0,"playerAugment4":0,"playerAugment5":0,"playerAugment6":0,"playerSubteamId":0,"profileIcon":6106,"pushPings":0,"puuid":"hyABV_8PhuV-sZhNZdQU8n_x3W_psoxtbG1ORjDBCjEqyAccAshPzGp-14O1HFaORZvDP-Fcb0GKmg","quadraKills":0,"retreatPings":0,"riotIdGameName":"Filin","riotIdTagline":"EUW","role":"SUPPORT","roleBoundItem":1208,"sightWardsBoughtInGame":0,"spell1Casts":83,"spell2Casts":55,"spell3Casts":40,"spell4Casts":11,"subteamPlacement":0,"summoner1Casts":5,"summoner1Id":4,"summoner2Casts":6,"summoner2Id":7,"summonerId":"ntUVngPHgtnrQm3HxsHFbc-y3RWYvvE1duxpVIOrtzAahPw","summonerLevel":292,"summonerName":"","teamEarlySurrendered":false,"teamId":100,"teamPosition":"UTILITY","timeCCingOthers":35,"timePlayed":1910,"totalAllyJungleMinionsKilled":0,"totalDamageDealt":52793,"totalDamageDealtToChampions":30287,"totalDamageShieldedOnTeammates":0,"totalDamageTaken":29318,"totalEnemyJungleMinionsKilled":0,"totalHeal":2482,"totalHealsOnTeammates":683,"totalMinionsKilled":44,"totalTimeCCDealt":171,"totalTimeSpentDead":387,"totalUnitsHealed":3,"tripleKills":0,"trueDamageDealt":10163,"trueDamageDealtToChampions":8350,"trueDamageTaken":2143,"turretKills":0,"turretTakedowns":0,"turretsLost":11,"unrealKills":0,"visionClearedPings":0,"visionScore":58,"visionWardsBoughtInGame":1,"wardsKilled":5,"wardsPlaced":21,"win":false},{"PlayerBehavior":{"PlayerBehavior_IsHeroInCombat":0},"PlayerScore0":0,"PlayerScore1":0,"PlayerScore10":0,"PlayerScore11":0,"PlayerScore2":0,"PlayerScore3":0,"PlayerScore4":0,"PlayerScore5":0,"PlayerScore6":0,"PlayerScore7":0,"PlayerScore8":0,"PlayerScore9":0,"allInPings":0,"assistMePings":5,"assists":3,"baronKills":0,"basicPings":0,"challenges":{"12AssistStreakCount":0,"HealFromMapSources":988,"InfernalScalePickup":0,"SWARM_DefeatAatrox":0,"SWARM_DefeatBriar":0,"SWARM_DefeatMiniBosses":0,"SWARM_EvolveWeapon":0,"SWARM_Have3Passives":0,"SWARM_KillEnemy":0,"SWARM_PickupGold":0,"SWARM_ReachLevel50":0,"SWARM_Survive15Min":0,"SWARM_WinWith5EvolvedWeapons":0,"abilityUses":224,"acesBefore15Minutes":0,"alliedJungleMonsterKills":3,"baronBuffGoldAdvantageOverThreshold":1,"baronTakedowns":1,"blastConeOppositeOpponentCount":0,"bountyGold":137.99996948242188,"buffsStolen":0,"completeSupportQuestInTime":0,"controlWardsPlaced":0,"damagePerMinute":1206.9365948796337,"damageTakenOnTeamPercentage":0.21347428736874088,"dancedWithRiftHerald":0,"deathsByEnemyChamps":5,"dodgeSkillShotsSmallWindow":6,"doubleAces":0,"dragonTakedowns":1,"earliestBaron":1732.0665691230001,"earliestDragonTakedown":1199.659388581,"earlyLaningPhaseGoldExpAdvantage":1,"effectiveHealAndShielding":0,"elderDragonKillsWithOpposingSoul":0,"elderDragonMultikills":0,"enemyChampionImmobilizations":2,"enemyJungleMonsterKills":0,"epicMonsterKillsNearEnemyJungler":0,"epicMonsterKillsWithin30SecondsOfSpawn":0,"epicMonsterSteals":0,"epicMonsterStolenWithoutSmite":0,"firstTurretKilled":1,"firstTurretKilledTime":822.221186521,"fistBumpParticipation":0,"flawlessAces":1,"fullTeamTakedown":0,"gameLength":1910.5834197570002,"getTakedownsInAllLanesEarlyJungleAsLaner":0,"goldPerMinute":549.3272762049753,"hadOpenNexus":0,"immobilizeAndKillWithAlly":0,"initialBuffCount":0,"initialCrabCount":0,"jungleCsBefore10Minutes":0,"junglerTakedownsNearDamagedEpicMonster":0,"kTurretsDestroyedBeforePlatesFall":1,"kda":3.8,"killAfterHiddenWithAlly":2,"killParticipation":0.40425531914893614,"killedChampTookFullTeamDamageSurvived":0,"killingSprees":2,"killsNearEnemyTurret":2,"killsOnOtherLanesEarlyJungleAsLaner":0,"killsOnRecentlyHealedByAramPack":0,"killsUnderOwnTurret":0,"killsWithHelpFromEpicMonster":0,"knockEnemyIntoTeamAndKill":0,"landSkillShotsEarlyGame":0,"laneMinionsFirst10Minutes":61,"laningPhaseGoldExpAdvantage":1,"legendaryCount":0,"legendaryItemUsed":[6698,6676,3031,3036],"lostAnInhibitor":0,"maxCsAdvantageOnLaneOpponent":74,"maxKillDeficit":5,"maxLevelLeadLaneOpponent":3,"mejaisFullStackInTime":0,"moreEnemyJungleThanOpponent":0,"multiKillOneSpell":0,"multiTurretRiftHeraldCount":0,"multikills":3,"multikillsAfterAggressiveFlash":1,"outerTurretExecutesBefore10Minutes":0,"outnumberedKills":1,"outnumberedNexusKill":0,"perfectDragonSoulsTaken":1,"perfectGame":0,"pickKillWithAlly":14,"playedChampSelectPosition":1,"poroExplosions":0,"quickCleanse":0,"quickFirstTurret":0,"quickSoloKills":1,"riftHeraldTakedowns":1,"saveAllyFromDeath":0,"scuttleCrabKills":2,"shortestTimeToAceFromFirstTakedown":4.688603634999936,"skillshotsDodged":45,"skillshotsHit":0,"snowballsHit":0,"soloBaronKills":0,"soloKills":3,"soloTurretsLategame":1,"stealthWardsPlaced":9,"survivedSingleDigitHpCount":0,"survivedThreeImmobilizesInFight":1,"takedownOnFirstTurret":1,"takedowns":19,"takedownsAfterGainingLevelAdvantage":0,"takedownsBeforeJungleMinionSpawn":0,"takedownsFirstXMinutes":3,"takedownsInAlcove":0,"takedownsInEnemyFountain":0,"teamBaronKills":1,"teamDamagePercentage":0.30200355590520994,"teamElderDragonKills":0,"teamRiftHeraldKills":1,"tookLargeDamageSurvived":0,"turretPlatesTaken":18,"turretTakedowns":4,"turretsTakenWithRiftHerald":0,"twentyMinionsIn3SecondsCount":0,"twoWardsOneSweeperCount":0,"unseenRecalls":0,"visionScoreAdvantageLaneOpponent":0.31778836250305176,"visionScorePerMinute":1.0850259993305253,"voidMonsterKill":2,"wardTakedowns":3,"wardTakedownsBefore20M":1,"wardsGuarded":0},"champExperience":18743,"champLevel":18,"championId":23,"championName":"Tryndamere","championTransform":0,"commandPings":3,"consumablesPurchased":1,"damageDealtToBuildings":18340,"damageDealtToEpicMonsters":22391,"damageDealtToObjectives":40732,"damageDealtToTurrets":18340,"damageSelfMitigated":30544,"dangerPings":0,"deaths":5,"detectorWardsPlaced":0,"doubleKills":2,"dragonKills":0,"eligibleForProgression":true,"enemyMissingPings":1,"enemyVisionPings":0,"firstBloodAssist":false,"firstBloodKill":false,"firstTowerAssist":false,"firstTowerKill":true,"gameEndedInEarlySurrender":false,"gameEndedInSurrender":false,"getBackPings":1,"goldEarned":17492,"goldSpent":15125,"holdPings":0,"individualPosition":"TOP","inhibitorKills":0,"inhibitorTakedowns":1,"inhibitorsLost":0,"item0":3006,"item1":6698,"item2":6676,"item3":3031,"item4":3036,"item5":1037,"item6":3340,"itemsPurchased":28,"killingSprees":4,"kills":16,"lane":"TOP","largestCriticalStrike":1490,"largestKillingSpree":6,"largestMultiKill":3,"longestTimeSpentLiving":633,"magicDamageDealt":0,"magicDamageDealtToChampions":0,"magicDamageTaken":13454,"missions":{"playerScore0":0,"playerScore1":0,"playerScore2":0,"playerScore3":0,"playerScore4":0,"playerScore5":0,"playerScore6":0,"playerScore7":0,"playerScore8":0,"playerScore9":0,"playerScore10":0,"playerScore11":0},"needVisionPings":0,"neutralMinionsKilled":20,"nexusKills":1,"nexusLost":0,"nexusTakedowns":1,"objectivesStolen":0,"objectivesStolenAssists":0,"onMyWayPings":6,"participantId":6,"pentaKills":0,"perks":{"statPerks":{"defense":5011,"flex":5008,"offense":5008},"styles":[{"description":"primaryStyle","selections":[{"perk":9923,"var1":68,"var2":83,"var3":0},{"perk":8143,"var1":1487,"var2":0,"var3":0},{"perk":8140,"var1":18,"var2":0,"var3":0},{"perk":8106,"var1":5,"var2":31,"var3":0}],"style":8100},{"description":"subStyle","selections":[{"perk":8299,"var1":2812,"var2":0,"var3":0},{"perk":9104,"var1":16,"var2":20,"var3":0}],"style":8000}]},"physicalDamageDealt":209779,"physicalDamageDealtToChampions":35387,"physicalDamageTaken":20340,"placement":0,"playerAugment1":0,"playerAugment2":0,"playerAugment3":0,"playerAugment4":0,"playerAugment5":0,"playerAugment6":0,"playerSubteamId":0,"profileIcon":5536,"pushPings":0,"puuid":"LwbnMHSpYQvvsGEjz_MMsJIX-DBg1yFaAdDC8bV-lnKNPyg8eRSgB2a7xgrksP5-vi6WXbh9Ijmzew","quadraKills":0,"retreatPings":0,"riotIdGameName":"Gerzukii","riotIdTagline":"NEGRA","role":"SOLO","roleBoundItem":1220,"sightWardsBoughtInGame":0,"spell1Casts":42,"spell2Casts":37,"spell3Casts":135,"spell4Casts":10,"subteamPlacement":0,"summoner1Casts":5,"summoner1Id":4,"summoner2Casts":6,"summoner2Id":14,"summonerId":"soSh3HX7TatQGLj0tWx111sGansygJ_RIO_itYQiyXe5JBDZ","summonerLevel":209,"summonerName":"","teamEarlySurrendered":false,"teamId":200,"teamPosition":"TOP","timeCCingOthers":24,"timePlayed":1910,"totalAllyJungleMinionsKilled":6,"totalDamageDealt":231159,"totalDamageDealtToChampions":38432,"totalDamageShieldedOnTeammates":0,"totalDamageTaken":35975,"totalEnemyJungleMinionsKilled":0,"totalHeal":16027,"totalHealsOnTeammates":0,"totalMinionsKilled":192,"totalTimeCCDealt":170,"totalTimeSpentDead":179,"totalUnitsHealed":1,"tripleKills":1,"trueDamageDealt":21380,"trueDamageDealtToChampions":3044,"trueDamageTaken":2180,"turretKills":4,"turretTakedowns":4,"turretsLost":3,"unrealKills":0,"visionClearedPings":0,"visionScore":34,"visionWardsBoughtInGame":0,"wardsKilled":3,"wardsPlaced":9,"win":true},{"PlayerBehavior":{"PlayerBehavior_IsHeroInCombat":0},"PlayerScore0":0,"PlayerScore1":0,"PlayerScore10":0,"PlayerScore11":0,"PlayerScore2":0,"PlayerScore3":0,"PlayerScore4":0,"PlayerScore5":0,"PlayerScore6":0,"PlayerScore7":0,"PlayerScore8":0,"PlayerScore9":0,"allInPings":0,"assistMePings":3,"assists":11,"baronKills":1,"basicPings":0,"challenges":{"12AssistStreakCount":0,"HealFromMapSources":1009.4256744384766,"InfernalScalePickup":0,"SWARM_DefeatAatrox":0,"SWARM_DefeatBriar":0,"SWARM_DefeatMiniBosses":0,"SWARM_EvolveWeapon":0,"SWARM_Have3Passives":0,"SWARM_KillEnemy":0,"SWARM_PickupGold":0,"SWARM_ReachLevel50":0,"SWARM_Survive15Min":0,"SWARM_WinWith5EvolvedWeapons":0,"abilityUses":231,"acesBefore15Minutes":0,"alliedJungleMonsterKills":85,"baronBuffGoldAdvantageOverThreshold":1,"baronTakedowns":1,"blastConeOppositeOpponentCount":0,"bountyGold":370.49176025390625,"buffsStolen":1,"completeSupportQuestInTime":0,"controlWardTimeCoverageInRiverOrEnemyHalf":0.736015924722016,"controlWardsPlaced":3,"damagePerMinute":547.6345259217078,"damageTakenOnTeamPercentage":0.22555987313218923,"dancedWithRiftHerald":0,"deathsByEnemyChamps":6,"dodgeSkillShotsSmallWindow":16,"doubleAces":0,"dragonTakedowns":4,"earliestBaron":1732.0665691230001,"earliestDragonTakedown":383.739973129,"earlyLaningPhaseGoldExpAdvantage":0,"effectiveHealAndShielding":0,"elderDragonKillsWithOpposingSoul":0,"elderDragonMultikills":0,"enemyChampionImmobilizations":7,"enemyJungleMonsterKills":13,"epicMonsterKillsNearEnemyJungler":2,"epicMonsterKillsWithin30SecondsOfSpawn":0,"epicMonsterSteals":0,"epicMonsterStolenWithoutSmite":0,"firstTurretKilled":1,"firstTurretKilledTime":822.221186521,"fistBumpParticipation":0,"flawlessAces":1,"fullTeamTakedown":0,"gameLength":1910.5834197570002,"goldPerMinute":449.2181606183989,"hadOpenNexus":0,"highestCrowdControlScore":1,"immobilizeAndKillWithAlly":3,"initialBuffCount":2,"initialCrabCount":2,"jungleCsBefore10Minutes":54.00000008940697,"junglerKillsEarlyJungle":0,"junglerTakedownsNearDamagedEpicMonster":0,"kTurretsDestroyedBeforePlatesFall":0,"kda":3.1666666666666665,"killAfterHiddenWithAlly":1,"killParticipation":0.40425531914893614,"killedChampTookFullTeamDamageSurvived":0,"killingSprees":2,"killsNearEnemyTurret":3,"killsOnLanersEarlyJungleAsJungler":2,"killsOnRecentlyHealedByAramPack":0,"killsUnderOwnTurret":0,"killsWithHelpFromEpicMonster":0,"knockEnemyIntoTeamAndKill":0,"landSkillShotsEarlyGame":5,"laneMinionsFirst10Minutes":3,"laningPhaseGoldExpAdvantage":0,"legendaryCount":0,"legendaryItemUsed":[6631,3073,3071],"lostAnInhibitor":0,"maxCsAdvantageOnLaneOpponent":10.750000029802322,"maxKillDeficit":5,"maxLevelLeadLaneOpponent":2,"mejaisFullStackInTime":0,"moreEnemyJungleThanOpponent":-33.00000002980232,"multiKillOneSpell":0,"multiTurretRiftHeraldCount":0,"multikills":1,"multikillsAfterAggressiveFlash":0,"outerTurretExecutesBefore10Minutes":0,"outnumberedKills":1,"outnumberedNexusKill":0,"perfectDragonSoulsTaken":1,"perfectGame":0,"pickKillWithAlly":13,"playedChampSelectPosition":1,"poroExplosions":0,"quickCleanse":0,"quickFirstTurret":0,"quickSoloKills":0,"riftHeraldTakedowns":1,"saveAllyFromDeath":0,"scuttleCrabKills":4,"skillshotsDodged":118,"skillshotsHit":21,"snowballsHit":0,"soloBaronKills":0,"soloKills":3,"stealthWardsPlaced":17,"survivedSingleDigitHpCount":0,"survivedThreeImmobilizesInFight":0,"takedownOnFirstTurret":0,"takedowns":19,"takedownsAfterGainingLevelAdvantage":0,"takedownsBeforeJungleMinionSpawn":0,"takedownsFirstXMinutes":3,"takedownsInAlcove":0,"takedownsInEnemyFountain":0,"teamBaronKills":1,"teamDamagePercentage":0.13703087209922032,"teamElderDragonKills":0,"teamRiftHeraldKills":1,"tookLargeDamageSurvived":0,"turretPlatesTaken":3,"turretTakedowns":0,"turretsTakenWithRiftHerald":0,"twentyMinionsIn3SecondsCount":0,"twoWardsOneSweeperCount":0,"unseenRecalls":0,"visionScoreAdvantageLaneOpponent":0.7318671941757202,"visionScorePerMinute":1.3385005166937465,"voidMonsterKill":3,"wardTakedowns":4,"wardTakedownsBefore20M":2,"wardsGuarded":0},"champExperience":17455,"champLevel":17,"championId":56,"championName":"Nocturne","championTransform":0,"commandPings":1,"consumablesPurchased":5,"damageDealtToBuildings":61,"damageDealtToEpicMonsters":31932,"damageDealtToObjectives":31994,"damageDealtToTurrets":61,"damageSelfMitigated":23214,"dangerPings":0,"deaths":6,"detectorWardsPlaced":3,"doubleKills":1,"dragonKills":4,"eligibleForProgression":true,"enemyMissingPings":0,"enemyVisionPings":0,"firstBloodAssist":false,"firstBloodKill":false,"firstTowerAssist":false,"firstTowerKill":false,"gameEndedInEarlySurrender":false,"gameEndedInSurrender":false,"getBackPings":0,"goldEarned":14304,"goldSpent":13450,"holdPings":0,"individualPosition":"JUNGLE","inhibitorKills":0,"inhibitorTakedowns":0,"inhibitorsLost":0,"item0":6631,"item1":3047,"item2":3073,"item3":3071,"item4":3133,"item5":2019,"item6":3340,"itemsPurchased":27,"killingSprees":2,"kills":8,"lane":"JUNGLE","largestCriticalStrike":0,"largestKillingSpree":4,"largestMultiKill":2,"longestTimeSpentLiving":739,"magicDamageDealt":6328,"magicDamageDealtToChampions":1416,"magicDamageTaken":11907,"missions":{"playerScore0":0,"playerScore1":0,"playerScore2":0,"playerScore3":0,"playerScore4":0,"playerScore5":0,"playerScore6":0,"playerScore7":0,"playerScore8":0,"playerScore9":0,"playerScore10":0,"playerScore11":0},"needVisionPings":0,"neutralMinionsKilled":182,"nexusKills":0,"nexusLost":0,"nexusTakedowns":0,"objectivesStolen":0,"objectivesStolenAssists":0,"onMyWayPings":10,"participantId":7,"pentaKills":0,"perks":{"statPerks":{"defense":5001,"flex":5008,"offense":5005},"styles":[{"description":"primaryStyle","selections":[{"perk":8010,"var1":322,"var2":0,"var3":0},{"perk":9111,"var1":1869,"var2":380,"var3":0},{"perk":9104,"var1":14,"var2":0,"var3":0},{"perk":8299,"var1":397,"var2":0,"var3":0}],"style":8000},{"description":"subStyle","selections":[{"perk":8106,"var1":5,"var2":31,"var3":0},{"perk":8140,"var1":18,"var2":0,"var3":0}],"style":8100}]},"physicalDamageDealt":155082,"physicalDamageDealtToChampions":14490,"physicalDamageTaken":24603,"placement":0,"playerAugment1":0,"playerAugment2":0,"playerAugment3":0,"playerAugment4":0,"playerAugment5":0,"playerAugment6":0,"playerSubteamId":0,"profileIcon":1591,"pushPings":0,"puuid":"ivSKQjxSZA6gZvS2BIDZYVXUmBf8NKkoEAatfCFzXswSQKmyOq_CMuwYCw1L9rRbEmJKO7knz5UpfQ","quadraKills":0,"retreatPings":2,"riotIdGameName":"TimTomYam","riotIdTagline":"EUW","role":"NONE","roleBoundItem":1209,"sightWardsBoughtInGame":0,"spell1Casts":118,"spell2Casts":24,"spell3Casts":66,"spell4Casts":23,"subteamPlacement":0,"summoner1Casts":19,"summoner1Id":11,"summoner2Casts":5,"summoner2Id":4,"summonerId":"s97v5GBmTbZJ2EeH88lk96RHzE7jHEvfRy_1nDx5unh34CP3ESuzSxxkyw","summonerLevel":347,"summonerName":"","teamEarlySurrendered":false,"teamId":200,"teamPosition":"JUNGLE","timeCCingOthers":181,"timePlayed":1910,"totalAllyJungleMinionsKilled":122,"totalDamageDealt":248002,"totalDamageDealtToChampions":17438,"totalDamageShieldedOnTeammates":0,"totalDamageTaken":38012,"totalEnemyJungleMinionsKilled":13,"totalHeal":16222,"totalHealsOnTeammates":0,"totalMinionsKilled":18,"totalTimeCCDealt":880,"totalTimeSpentDead":219,"totalUnitsHealed":1,"tripleKills":0,"trueDamageDealt":86592,"trueDamageDealtToChampions":1532,"trueDamageTaken":1501,"turretKills":0,"turretTakedowns":0,"turretsLost":3,"unrealKills":0,"visionClearedPings":0,"visionScore":42,"visionWardsBoughtInGame":4,"wardsKilled":4,"wardsPlaced":20,"win":true},{"PlayerBehavior":{"PlayerBehavior_IsHeroInCombat":0},"PlayerScore0":0,"PlayerScore1":0,"PlayerScore10":0,"PlayerScore11":0,"PlayerScore2":0,"PlayerScore3":0,"PlayerScore4":0,"PlayerScore5":0,"PlayerScore6":0,"PlayerScore7":0,"PlayerScore8":0,"PlayerScore9":0,"allInPings":0,"assistMePings":0,"assists":11,"baronKills":0,"basicPings":0,"challenges":{"12AssistStreakCount":0,"HealFromMapSources":1294,"InfernalScalePickup":0,"SWARM_DefeatAatrox":0,"SWARM_DefeatBriar":0,"SWARM_DefeatMiniBosses":0,"SWARM_EvolveWeapon":0,"SWARM_Have3Passives":0,"SWARM_KillEnemy":0,"SWARM_PickupGold":0,"SWARM_ReachLevel50":0,"SWARM_Survive15Min":0,"SWARM_WinWith5EvolvedWeapons":0,"abilityUses":285,"acesBefore15Minutes":0,"alliedJungleMonsterKills":0,"baronBuffGoldAdvantageOverThreshold":1,"baronTakedowns":0,"blastConeOppositeOpponentCount":0,"bountyGold":0,"buffsStolen":0,"completeSupportQuestInTime":0,"controlWardsPlaced":0,"damagePerMinute":425.605373680005,"damageTakenOnTeamPercentage":0.16599373022616007,"dancedWithRiftHerald":0,"deathsByEnemyChamps":6,"dodgeSkillShotsSmallWindow":4,"doubleAces":0,"dragonTakedowns":0,"earliestBaron":1732.0665691230001,"earlyLaningPhaseGoldExpAdvantage":0,"effectiveHealAndShielding":0,"elderDragonKillsWithOpposingSoul":0,"elderDragonMultikills":0,"enemyChampionImmobilizations":23,"enemyJungleMonsterKills":0,"epicMonsterKillsNearEnemyJungler":0,"epicMonsterKillsWithin30SecondsOfSpawn":0,"epicMonsterSteals":0,"epicMonsterStolenWithoutSmite":0,"firstTurretKilled":1,"firstTurretKilledTime":822.221186521,"fistBumpParticipation":0,"flawlessAces":1,"fullTeamTakedown":0,"gameLength":1910.5834197570002,"getTakedownsInAllLanesEarlyJungleAsLaner":0,"goldPerMinute":348.23782881965013,"hadOpenNexus":0,"immobilizeAndKillWithAlly":6,"initialBuffCount":0,"initialCrabCount":0,"jungleCsBefore10Minutes":0,"junglerTakedownsNearDamagedEpicMonster":0,"kTurretsDestroyedBeforePlatesFall":0,"kda":2,"killAfterHiddenWithAlly":1,"killParticipation":0.2553191489361702,"killedChampTookFullTeamDamageSurvived":0,"killingSprees":0,"killsNearEnemyTurret":1,"killsOnOtherLanesEarlyJungleAsLaner":0,"killsOnRecentlyHealedByAramPack":0,"killsUnderOwnTurret":0,"killsWithHelpFromEpicMonster":0,"knockEnemyIntoTeamAndKill":2,"landSkillShotsEarlyGame":4,"laneMinionsFirst10Minutes":43,"laningPhaseGoldExpAdvantage":0,"legendaryCount":0,"legendaryItemUsed":[6698,3142,3814],"lostAnInhibitor":0,"maxCsAdvantageOnLaneOpponent":4,"maxKillDeficit":5,"maxLevelLeadLaneOpponent":1,"mejaisFullStackInTime":0,"moreEnemyJungleThanOpponent":0,"multiKillOneSpell":0,"multiTurretRiftHeraldCount":0,"multikills":0,"multikillsAfterAggressiveFlash":0,"outerTurretExecutesBefore10Minutes":0,"outnumberedKills":1,"outnumberedNexusKill":0,"perfectDragonSoulsTaken":1,"perfectGame":0,"pickKillWithAlly":10,"playedChampSelectPosition":1,"poroExplosions":0,"quickCleanse":0,"quickFirstTurret":0,"quickSoloKills":0,"riftHeraldTakedowns":0,"saveAllyFromDeath":0,"scuttleCrabKills":0,"skillshotsDodged":71,"skillshotsHit":15,"snowballsHit":0,"soloBaronKills":0,"soloKills":0,"stealthWardsPlaced":2,"survivedSingleDigitHpCount":0,"survivedThreeImmobilizesInFight":0,"takedownOnFirstTurret":0,"takedowns":12,"takedownsAfterGainingLevelAdvantage":0,"takedownsBeforeJungleMinionSpawn":0,"takedownsFirstXMinutes":1,"takedownsInAlcove":0,"takedownsInEnemyFountain":0,"teamBaronKills":1,"teamDamagePercentage":0.10649634521732744,"teamElderDragonKills":0,"teamRiftHeraldKills":1,"tookLargeDamageSurvived":0,"turretPlatesTaken":14,"turretTakedowns":3,"turretsTakenWithRiftHerald":0,"twentyMinionsIn3SecondsCount":0,"twoWardsOneSweeperCount":0,"unseenRecalls":0,"visionScoreAdvantageLaneOpponent":-0.5389195680618286,"visionScorePerMinute":0.5396778280029315,"voidMonsterKill":0,"wardTakedowns":5,"wardTakedownsBefore20M":1,"wardsGuarded":0},"champExperience":15379,"champLevel":16,"championId":246,"championName":"Qiyana","championTransform":0,"commandPings":0,"consumablesPurchased":1,"damageDealtToBuildings":12811,"damageDealtToEpicMonsters":0,"damageDealtToObjectives":12811,"damageDealtToTurrets":12811,"damageSelfMitigated":13790,"dangerPings":0,"deaths":6,"detectorWardsPlaced":0,"doubleKills":0,"dragonKills":0,"eligibleForProgression":true,"enemyMissingPings":1,"enemyVisionPings":0,"firstBloodAssist":false,"firstBloodKill":false,"firstTowerAssist":false,"firstTowerKill":false,"gameEndedInEarlySurrender":false,"gameEndedInSurrender":false,"getBackPings":0,"goldEarned":11088,"goldSpent":10050,"holdPings":0,"individualPosition":"MIDDLE","inhibitorKills":0,"inhibitorTakedowns":0,"inhibitorsLost":0,"item0":3142,"item1":3171,"item2":6698,"item3":1055,"item4":3814,"item5":0,"item6":3364,"itemsPurchased":24,"killingSprees":0,"kills":1,"lane":"MIDDLE","largestCriticalStrike":0,"largestKillingSpree":0,"largestMultiKill":1,"longestTimeSpentLiving":412,"magicDamageDealt":12150,"magicDamageDealtToChampions":1087,"magicDamageTaken":13509,"missions":{"playerScore0":0,"playerScore1":0,"playerScore2":0,"playerScore3":0,"playerScore4":0,"playerScore5":0,"playerScore6":0,"playerScore7":0,"playerScore8":0,"playerScore9":0,"playerScore10":0,"playerScore11":0},"needVisionPings":0,"neutralMinionsKilled":0,"nexusKills":0,"nexusLost":0,"nexusTakedowns":1,"objectivesStolen":0,"objectivesStolenAssists":0,"onMyWayPings":0,"participantId":8,"pentaKills":0,"perks":{"statPerks":{"defense":5001,"flex":5008,"offense":5008},"styles":[{"description":"primaryStyle","selections":[{"perk":8112,"var1":1003,"var2":0,"var3":0},{"perk":8143,"var1":1193,"var2":0,"var3":0},{"perk":8140,"var1":12,"var2":0,"var3":0},{"perk":8135,"var1":450,"var2":5,"var3":0}],"style":8100},{"description":"subStyle","selections":[{"perk":8009,"var1":1312,"var2":0,"var3":0},{"perk":8299,"var1":245,"var2":0,"var3":0}],"style":8000}]},"physicalDamageDealt":112201,"physicalDamageDealtToChampions":10767,"physicalDamageTaken":13667,"placement":0,"playerAugment1":0,"playerAugment2":0,"playerAugment3":0,"playerAugment4":0,"playerAugment5":0,"playerAugment6":0,"playerSubteamId":0,"profileIcon":7070,"pushPings":0,"puuid":"BYmN-uvrxzQhrRxtdBSMeuqfsaatwrR9xjjXQNEbuFH1SdIE7RR_dSgUFPGjLcLzQZf7w_DcFzwCWA","quadraKills":0,"retreatPings":3,"riotIdGameName":"Negan","riotIdTagline":"9111","role":"SOLO","roleBoundItem":1206,"sightWardsBoughtInGame":0,"spell1Casts":112,"spell2Casts":127,"spell3Casts":38,"spell4Casts":8,"subteamPlacement":0,"summoner1Casts":3,"summoner1Id":14,"summoner2Casts":6,"summoner2Id":4,"summonerId":"GLsuiyS2x4MzhoRjgrKgI8tkONpGjpoO4UyXrHgEU1zd_rAN","summonerLevel":174,"summonerName":"","teamEarlySurrendered":false,"teamId":200,"teamPosition":"MIDDLE","timeCCingOthers":16,"timePlayed":1910,"totalAllyJungleMinionsKilled":0,"totalDamageDealt":130747,"totalDamageDealtToChampions":13552,"totalDamageShieldedOnTeammates":0,"totalDamageTaken":27974,"totalEnemyJungleMinionsKilled":0,"totalHeal":7162,"totalHealsOnTeammates":0,"totalMinionsKilled":166,"totalTimeCCDealt":73,"totalTimeSpentDead":188,"totalUnitsHealed":1,"tripleKills":0,"trueDamageDealt":6395,"trueDamageDealtToChampions":1698,"trueDamageTaken":797,"turretKills":3,"turretTakedowns":3,"turretsLost":3,"unrealKills":0,"visionClearedPings":0,"visionScore":17,"visionWardsBoughtInGame":0,"wardsKilled":5,"wardsPlaced":2,"win":true},{"PlayerBehavior":{"PlayerBehavior_IsHeroInCombat":0},"PlayerScore0":0,"PlayerScore1":0,"PlayerScore10":0,"PlayerScore11":0,"PlayerScore2":0,"PlayerScore3":0,"PlayerScore4":0,"PlayerScore5":0,"PlayerScore6":0,"PlayerScore7":0,"PlayerScore8":0,"PlayerScore9":0,"allInPings":0,"assistMePings":1,"assists":10,"baronKills":0,"basicPings":0,"challenges":{"12AssistStreakCount":0,"HealFromMapSources":1946,"InfernalScalePickup":0,"SWARM_DefeatAatrox":0,"SWARM_DefeatBriar":0,"SWARM_DefeatMiniBosses":0,"SWARM_EvolveWeapon":0,"SWARM_Have3Passives":0,"SWARM_KillEnemy":0,"SWARM_PickupGold":0,"SWARM_ReachLevel50":0,"SWARM_Survive15Min":0,"SWARM_WinWith5EvolvedWeapons":0,"abilityUses":139,"acesBefore15Minutes":0,"alliedJungleMonsterKills":0,"baronBuffGoldAdvantageOverThreshold":1,"baronTakedowns":1,"blastConeOppositeOpponentCount":0,"bountyGold":128.011962890625,"buffsStolen":2,"completeSupportQuestInTime":0,"controlWardsPlaced":0,"damagePerMinute":1389.4724613556216,"damageTakenOnTeamPercentage":0.16429545834919118,"dancedWithRiftHerald":0,"deathsByEnemyChamps":6,"dodgeSkillShotsSmallWindow":26,"doubleAces":0,"dragonTakedowns":1,"earliestBaron":1732.0665691230001,"earliestDragonTakedown":383.739973129,"earlyLaningPhaseGoldExpAdvantage":0,"effectiveHealAndShielding":0,"elderDragonKillsWithOpposingSoul":0,"elderDragonMultikills":0,"enemyChampionImmobilizations":0,"enemyJungleMonsterKills":8,"epicMonsterKillsNearEnemyJungler":0,"epicMonsterKillsWithin30SecondsOfSpawn":0,"epicMonsterSteals":0,"epicMonsterStolenWithoutSmite":0,"firstTurretKilled":1,"firstTurretKilledTime":822.221186521,"fistBumpParticipation":0,"flawlessAces":1,"fullTeamTakedown":0,"gameLength":1910.5834197570002,"getTakedownsInAllLanesEarlyJungleAsLaner":0,"goldPerMinute":617.6146430837761,"hadOpenNexus":0,"highestChampionDamage":1,"highestWardKills":1,"immobilizeAndKillWithAlly":0,"initialBuffCount":0,"initialCrabCount":0,"jungleCsBefore10Minutes":0,"junglerTakedownsNearDamagedEpicMonster":0,"kTurretsDestroyedBeforePlatesFall":0,"kda":4.833333333333333,"killAfterHiddenWithAlly":1,"killParticipation":0.6170212765957447,"killedChampTookFullTeamDamageSurvived":0,"killingSprees":2,"killsNearEnemyTurret":3,"killsOnOtherLanesEarlyJungleAsLaner":0,"killsOnRecentlyHealedByAramPack":0,"killsUnderOwnTurret":1,"killsWithHelpFromEpicMonster":0,"knockEnemyIntoTeamAndKill":0,"landSkillShotsEarlyGame":4,"laneMinionsFirst10Minutes":69,"laningPhaseGoldExpAdvantage":0,"legendaryCount":0,"legendaryItemUsed":[6676,2512,3031,3026,3814],"lostAnInhibitor":0,"maxCsAdvantageOnLaneOpponent":39.00000002980232,"maxKillDeficit":5,"maxLevelLeadLaneOpponent":4,"mejaisFullStackInTime":0,"moreEnemyJungleThanOpponent":0,"multiKillOneSpell":0,"multiTurretRiftHeraldCount":0,"multikills":5,"multikillsAfterAggressiveFlash":0,"outerTurretExecutesBefore10Minutes":0,"outnumberedKills":11,"outnumberedNexusKill":0,"perfectDragonSoulsTaken":1,"perfectGame":0,"pickKillWithAlly":18,"playedChampSelectPosition":1,"poroExplosions":0,"quickCleanse":0,"quickFirstTurret":0,"quickSoloKills":0,"riftHeraldTakedowns":0,"saveAllyFromDeath":0,"scuttleCrabKills":1,"skillshotsDodged":171,"skillshotsHit":12,"snowballsHit":0,"soloBaronKills":0,"soloKills":8,"soloTurretsLategame":1,"stealthWardsPlaced":2,"survivedSingleDigitHpCount":0,"survivedThreeImmobilizesInFight":0,"takedownOnFirstTurret":0,"takedowns":29,"takedownsAfterGainingLevelAdvantage":0,"takedownsBeforeJungleMinionSpawn":0,"takedownsFirstXMinutes":8,"takedownsInAlcove":0,"takedownsInEnemyFountain":0,"teamBaronKills":1,"teamDamagePercentage":0.34767826739366603,"teamElderDragonKills":0,"teamRiftHeraldKills":1,"tookLargeDamageSurvived":0,"turretPlatesTaken":14,"turretTakedowns":5,"turretsTakenWithRiftHerald":0,"twentyMinionsIn3SecondsCount":0,"twoWardsOneSweeperCount":1,"unseenRecalls":0,"visionScoreAdvantageLaneOpponent":0.7658959627151489,"visionScorePerMinute":0.6100830835073862,"voidMonsterKill":1,"wardTakedowns":6,"wardTakedownsBefore20M":3,"wardsGuarded":0},"champExperience":19451,"champLevel":18,"championId":29,"championName":"Twitch","championTransform":0,"commandPings":15,"consumablesPurchased":1,"damageDealtToBuildings":13546,"damageDealtToEpicMonsters":6598,"damageDealtToObjectives":20145,"damageDealtToTurrets":13546,"damageSelfMitigated":15364,"dangerPings":0,"deaths":6,"detectorWardsPlaced":0,"doubleKills":5,"dragonKills":0,"eligibleForProgression":true,"enemyMissingPings":0,"enemyVisionPings":0,"firstBloodAssist":false,"firstBloodKill":false,"firstTowerAssist":false,"firstTowerKill":false,"gameEndedInEarlySurrender":false,"gameEndedInSurrender":false,"getBackPings":0,"goldEarned":19666,"goldSpent":16950,"holdPings":0,"individualPosition":"BOTTOM","inhibitorKills":1,"inhibitorTakedowns":1,"inhibitorsLost":0,"item0":1055,"item1":6676,"item2":2512,"item3":3031,"item4":3026,"item5":3814,"item6":3364,"itemsPurchased":26,"killingSprees":4,"kills":19,"lane":"BOTTOM","largestCriticalStrike":1208,"largestKillingSpree":7,"largestMultiKill":2,"longestTimeSpentLiving":577,"magicDamageDealt":345,"magicDamageDealtToChampions":176,"magicDamageTaken":11256,"missions":{"playerScore0":0,"playerScore1":0,"playerScore2":0,"playerScore3":0,"playerScore4":0,"playerScore5":0,"playerScore6":0,"playerScore7":0,"playerScore8":0,"playerScore9":0,"playerScore10":0,"playerScore11":0},"needVisionPings":0,"neutralMinionsKilled":16,"nexusKills":0,"nexusLost":0,"nexusTakedowns":0,"objectivesStolen":0,"objectivesStolenAssists":0,"onMyWayPings":0,"participantId":9,"pentaKills":0,"perks":{"statPerks":{"defense":5011,"flex":5008,"offense":5005},"styles":[{"description":"primaryStyle","selections":[{"perk":8005,"var1":2663,"var2":2663,"var3":0},{"perk":9111,"var1":2153,"var2":580,"var3":0},{"perk":9104,"var1":12,"var2":20,"var3":0},{"perk":8017,"var1":1471,"var2":0,"var3":0}],"style":8000},{"description":"subStyle","selections":[{"perk":8224,"var1":87,"var2":1667,"var3":0},{"perk":8236,"var1":28,"var2":0,"var3":0}],"style":8200}]},"physicalDamageDealt":188359,"physicalDamageDealtToChampions":39032,"physicalDamageTaken":13985,"placement":0,"playerAugment1":0,"playerAugment2":0,"playerAugment3":0,"playerAugment4":0,"playerAugment5":0,"playerAugment6":0,"playerSubteamId":0,"profileIcon":503,"pushPings":0,"puuid":"4N58newygntP4-ww9b-0r-H4qzxUO9SfzyQ-SrAv-Km9zGcGu-2zzTdaCmUAV66OK49nRLbB54N8XA","quadraKills":0,"retreatPings":1,"riotIdGameName":"Hail King Kira","riotIdTagline":"EUW","role":"CARRY","roleBoundItem":3006,"sightWardsBoughtInGame":0,"spell1Casts":53,"spell2Casts":38,"spell3Casts":32,"spell4Casts":16,"subteamPlacement":0,"summoner1Casts":4,"summoner1Id":4,"summoner2Casts":5,"summoner2Id":21,"summonerId":"qHslQ0ughmc7SnSFWicAytBxeFMGHp-MeE_Mftw2Uy0Hd1Q","summonerLevel":591,"summonerName":"","teamEarlySurrendered":false,"teamId":200,"teamPosition":"BOTTOM","timeCCingOthers":13,"timePlayed":1910,"totalAllyJungleMinionsKilled":0,"totalDamageDealt":201801,"totalDamageDealtToChampions":44245,"totalDamageShieldedOnTeammates":0,"totalDamageTaken":27687,"totalEnemyJungleMinionsKilled":12,"totalHeal":11569,"totalHealsOnTeammates":0,"totalMinionsKilled":203,"totalTimeCCDealt":318,"totalTimeSpentDead":152,"totalUnitsHealed":1,"tripleKills":0,"trueDamageDealt":13097,"trueDamageDealtToChampions":5036,"trueDamageTaken":2445,"turretKills":3,"turretTakedowns":5,"turretsLost":3,"unrealKills":0,"visionClearedPings":0,"visionScore":19,"visionWardsBoughtInGame":0,"wardsKilled":6,"wardsPlaced":2,"win":true},{"PlayerBehavior":{"PlayerBehavior_IsHeroInCombat":0},"PlayerScore0":0,"PlayerScore1":0,"PlayerScore10":0,"PlayerScore11":0,"PlayerScore2":0,"PlayerScore3":0,"PlayerScore4":0,"PlayerScore5":0,"PlayerScore6":0,"PlayerScore7":0,"PlayerScore8":0,"PlayerScore9":0,"allInPings":2,"assistMePings":5,"assists":16,"baronKills":0,"basicPings":0,"challenges":{"12AssistStreakCount":1,"HealFromMapSources":0,"InfernalScalePickup":0,"SWARM_DefeatAatrox":0,"SWARM_DefeatBriar":0,"SWARM_DefeatMiniBosses":0,"SWARM_EvolveWeapon":0,"SWARM_Have3Passives":0,"SWARM_KillEnemy":0,"SWARM_PickupGold":0,"SWARM_ReachLevel50":0,"SWARM_Survive15Min":0,"SWARM_WinWith5EvolvedWeapons":0,"abilityUses":115,"acesBefore15Minutes":0,"alliedJungleMonsterKills":0,"baronBuffGoldAdvantageOverThreshold":1,"baronTakedowns":1,"blastConeOppositeOpponentCount":0,"bountyGold":0,"buffsStolen":0,"completeSupportQuestInTime":1,"controlWardsPlaced":0,"damagePerMinute":426.7827790875565,"damageTakenOnTeamPercentage":0.2306766509237186,"dancedWithRiftHerald":0,"deathsByEnemyChamps":9,"dodgeSkillShotsSmallWindow":33,"doubleAces":0,"dragonTakedowns":0,"earliestBaron":1732.0665691230001,"earlyLaningPhaseGoldExpAdvantage":0,"effectiveHealAndShielding":0,"elderDragonKillsWithOpposingSoul":0,"elderDragonMultikills":0,"enemyChampionImmobilizations":130,"enemyJungleMonsterKills":0,"epicMonsterKillsNearEnemyJungler":0,"epicMonsterKillsWithin30SecondsOfSpawn":0,"epicMonsterSteals":0,"epicMonsterStolenWithoutSmite":0,"firstTurretKilled":1,"firstTurretKilledTime":822.221186521,"fistBumpParticipation":0,"flawlessAces":1,"fullTeamTakedown":0,"gameLength":1910.5834197570002,"getTakedownsInAllLanesEarlyJungleAsLaner":0,"goldPerMinute":320.66151107088047,"hadOpenNexus":0,"immobilizeAndKillWithAlly":14,"initialBuffCount":0,"initialCrabCount":0,"jungleCsBefore10Minutes":0,"junglerTakedownsNearDamagedEpicMonster":0,"kTurretsDestroyedBeforePlatesFall":0,"kda":2.111111111111111,"killAfterHiddenWithAlly":2,"killParticipation":0.40425531914893614,"killedChampTookFullTeamDamageSurvived":0,"killingSprees":0,"killsNearEnemyTurret":1,"killsOnOtherLanesEarlyJungleAsLaner":0,"killsOnRecentlyHealedByAramPack":0,"killsUnderOwnTurret":0,"killsWithHelpFromEpicMonster":0,"knockEnemyIntoTeamAndKill":7,"landSkillShotsEarlyGame":8,"laneMinionsFirst10Minutes":12,"laningPhaseGoldExpAdvantage":0,"legendaryCount":0,"legendaryItemUsed":[3876,3084,3075],"lostAnInhibitor":0,"maxCsAdvantageOnLaneOpponent":0,"maxKillDeficit":5,"maxLevelLeadLaneOpponent":2,"mejaisFullStackInTime":0,"moreEnemyJungleThanOpponent":0,"multiKillOneSpell":0,"multiTurretRiftHeraldCount":0,"multikills":1,"multikillsAfterAggressiveFlash":0,"outerTurretExecutesBefore10Minutes":0,"outnumberedKills":0,"outnumberedNexusKill":0,"perfectDragonSoulsTaken":1,"perfectGame":0,"pickKillWithAlly":17,"playedChampSelectPosition":1,"poroExplosions":0,"quickCleanse":0,"quickFirstTurret":0,"quickSoloKills":0,"riftHeraldTakedowns":0,"saveAllyFromDeath":0,"scuttleCrabKills":0,"shortestTimeToAceFromFirstTakedown":4.688603634999936,"skillshotsDodged":222,"skillshotsHit":23,"snowballsHit":0,"soloBaronKills":0,"soloKills":0,"stealthWardsPlaced":24,"survivedSingleDigitHpCount":0,"survivedThreeImmobilizesInFight":0,"takedownOnFirstTurret":0,"takedowns":19,"takedownsAfterGainingLevelAdvantage":0,"takedownsBeforeJungleMinionSpawn":0,"takedownsFirstXMinutes":6,"takedownsInAlcove":0,"takedownsInEnemyFountain":0,"teamBaronKills":1,"teamDamagePercentage":0.10679095938457624,"teamElderDragonKills":0,"teamRiftHeraldKills":1,"tookLargeDamageSurvived":0,"turretPlatesTaken":5,"turretTakedowns":1,"turretsTakenWithRiftHerald":0,"twentyMinionsIn3SecondsCount":0,"twoWardsOneSweeperCount":0,"unseenRecalls":0,"visionScoreAdvantageLaneOpponent":0.09731924533843994,"visionScorePerMinute":2.022182699075058,"voidMonsterKill":1,"wardTakedowns":4,"wardTakedownsBefore20M":1,"wardsGuarded":0},"champExperience":12975,"champLevel":14,"championId":111,"championName":"Nautilus","championTransform":0,"commandPings":2,"consumablesPurchased":7,"damageDealtToBuildings":776,"damageDealtToEpicMonsters":1233,"damageDealtToObjectives":2009,"damageDealtToTurrets":776,"damageSelfMitigated":41491,"dangerPings":0,"deaths":9,"detectorWardsPlaced":0,"doubleKills":1,"dragonKills":0,"eligibleForProgression":true,"enemyMissingPings":0,"enemyVisionPings":0,"firstBloodAssist":false,"firstBloodKill":false,"firstTowerAssist":false,"firstTowerKill":false,"gameEndedInEarlySurrender":false,"gameEndedInSurrender":false,"getBackPings":0,"goldEarned":10210,"goldSpent":9600,"holdPings":0,"individualPosition":"UTILITY","inhibitorKills":1,"inhibitorTakedowns":1,"inhibitorsLost":0,"item0":3876,"item1":3084,"item2":3111,"item3":3075,"item4":6660,"item5":3211,"item6":3364,"itemsPurchased":28,"killingSprees":1,"kills":3,"lane":"BOTTOM","largestCriticalStrike":7,"largestKillingSpree":2,"largestMultiKill":2,"longestTimeSpentLiving":276,"magicDamageDealt":22926,"magicDamageDealtToChampions":7423,"magicDamageTaken":18340,"missions":{"playerScore0":0,"playerScore1":0,"playerScore2":0,"playerScore3":0,"playerScore4":0,"playerScore5":0,"playerScore6":0,"playerScore7":0,"playerScore8":0,"playerScore9":0,"playerScore10":0,"playerScore11":0},"needVisionPings":0,"neutralMinionsKilled":0,"nexusKills":0,"nexusLost":0,"nexusTakedowns":0,"objectivesStolen":0,"objectivesStolenAssists":0,"onMyWayPings":5,"participantId":10,"pentaKills":0,"perks":{"statPerks":{"defense":5001,"flex":5001,"offense":5007},"styles":[{"description":"primaryStyle","selections":[{"perk":8439,"var1":1264,"var2":1290,"var3":0},{"perk":8401,"var1":505,"var2":0,"var3":0},{"perk":8473,"var1":970,"var2":0,"var3":0},{"perk":8242,"var1":188,"var2":0,"var3":0}],"style":8400},{"description":"subStyle","selections":[{"perk":8347,"var1":0,"var2":0,"var3":0},{"perk":8306,"var1":0,"var2":0,"var3":0}],"style":8300}]},"physicalDamageDealt":11864,"physicalDamageDealtToChampions":4781,"physicalDamageTaken":15333,"placement":0,"playerAugment1":0,"playerAugment2":0,"playerAugment3":0,"playerAugment4":0,"playerAugment5":0,"playerAugment6":0,"playerSubteamId":0,"profileIcon":7027,"pushPings":1,"puuid":"4098qF-YdL2oF6KZ6CfLLSZOq7huhopT3yWVUX7-F6bbKOKhnfippk5Ugf6CwCo2vm9SQPulokScQQ","quadraKills":0,"retreatPings":4,"riotIdGameName":"LuGiaOTP","riotIdTagline":"EUW","role":"SUPPORT","roleBoundItem":1208,"sightWardsBoughtInGame":0,"spell1Casts":37,"spell2Casts":33,"spell3Casts":36,"spell4Casts":9,"subteamPlacement":0,"summoner1Casts":8,"summoner1Id":14,"summoner2Casts":6,"summoner2Id":4,"summonerId":"vBFWifFLQZkpNJoQaeAgsYUTDakehvjG2W0o6MPWCE0uFUA","summonerLevel":1001,"summonerName":"","teamEarlySurrendered":false,"teamId":200,"teamPosition":"UTILITY","timeCCingOthers":81,"timePlayed":1910,"totalAllyJungleMinionsKilled":0,"totalDamageDealt":37659,"totalDamageDealtToChampions":13590,"totalDamageShieldedOnTeammates":0,"totalDamageTaken":38874,"totalEnemyJungleMinionsKilled":0,"totalHeal":4695,"totalHealsOnTeammates":0,"totalMinionsKilled":29,"totalTimeCCDealt":345,"totalTimeSpentDead":235,"totalUnitsHealed":1,"tripleKills":0,"trueDamageDealt":2869,"trueDamageDealtToChampions":1384,"trueDamageTaken":5200,"turretKills":1,"turretTakedowns":1,"turretsLost":3,"unrealKills":0,"visionClearedPings":0,"visionScore":64,"visionWardsBoughtInGame":0,"wardsKilled":4,"wardsPlaced":24,"win":true}],"platformId":"EUW1","queueId":420,"teams":[{"bans":[{"championId":117,"pickTurn":1},{"championId":904,"pickTurn":2},{"championId":222,"pickTurn":3},{"championId":82,"pickTurn":4},{"championId":53,"pickTurn":5}],"feats":{"EPIC_MONSTER_KILL":{"featState":0},"FIRST_BLOOD":{"featState":0},"FIRST_TURRET":{"featState":0}},"objectives":{"atakhan":{"first":false,"kills":0},"baron":{"first":false,"kills":0},"champion":{"first":true,"kills":32},"dragon":{"first":false,"kills":0},"horde":{"first":true,"kills":2},"inhibitor":{"first":false,"kills":0},"riftHerald":{"first":false,"kills":0},"tower":{"first":false,"kills":3}},"teamId":100,"win":false},{"bans":[{"championId":51,"pickTurn":6},{"championId":50,"pickTurn":7},{"championId":131,"pickTurn":8},{"championId":36,"pickTurn":9},{"championId":6,"pickTurn":10}],"feats":{"EPIC_MONSTER_KILL":{"featState":0},"FIRST_BLOOD":{"featState":0},"FIRST_TURRET":{"featState":0}},"objectives":{"atakhan":{"first":false,"kills":0},"baron":{"first":true,"kills":1},"champion":{"first":false,"kills":47},"dragon":{"first":true,"kills":4},"horde":{"first":false,"kills":1},"inhibitor":{"first":true,"kills":2},"riftHerald":{"first":true,"kills":1},"tower":{"first":true,"kills":11}},"teamId":200,"win":true}],"tournamentCode":""}}